{
  "board": "SB 17",
  "subject": "physics",
  "questions": [
    {
      "number": 1,
      "question": "$\\text{লেন্সের ক্ষমতা}+4D \\text{হলে}-i. \\text{ফোকাস দূরত্ব}25cmii. \\text{লেন্সটির আলোক কেন্দ্র হতে}2cm \\text{দূরে স্থাপিত বস্তুটির বিম্ব হবে অবাস্তব}iii. \\text{লেন্সটি হ্রস্ব দৃষ্টি প্রতিকারে সহায়ক লেন্স হিসাবে ব্যবহার করা যায়নিচের কোনটি সঠিক}?$",
      "image": null,
      "optionA": "$i \\text{ও}ii$",
      "optionA_img": null,
      "optionB": "$i \\text{ও}iii$",
      "optionB_img": null,
      "optionC": "$ii \\text{ও}iii$",
      "optionC_img": null,
      "optionD": "$i, ii \\text{ও}iii$",
      "optionD_img": null,
      "answer": "A",
      "chapter": "9",
      "explanation": "লেন্সের ক্ষমতা $P = +4D$। ফোকাস দূরত্ব $f = \\frac{1}{P} = \\frac{1}{4}m = 25cm$।  $i$. সঠিক। লেন্সের আলোক কেন্দ্র হতে 2cm দূরে স্থাপিত বস্তুর জন্য, বস্তু দূরত্ব $u = -2cm$। লেন্সের সূত্র  $\\frac{1}{v} - \\frac{1}{u} = \\frac{1}{f}$ ব্যবহার করে পাই, $\\frac{1}{v} = \\frac{1}{25} + \\frac{1}{-2} = \\frac{2 - 25}{50} = \\frac{-23}{50}$। সুতরাং, $v = -\\frac{50}{23} cm$। ঋণাত্মক চিহ্ন বোঝায় বিম্বটি অবাস্তব। $ii$. সঠিক।  $iii$. 4D ক্ষমতা সম্পন্ন উত্তল লেন্স হ্রস্বদৃষ্টি প্রতিকারে ব্যবহৃত হয়।  সুতরাং $i$ ও $ii$ সঠিক, তাই উত্তর A সঠিক।"
    },
    {
      "number": 2,
      "question": "$\\text{স্থির অবস্থান হতে সুষম ত্বরণে চলমান বস্তুর}-i. \\text{বেগ সময়ের সমানুপাতিক}ii. \\text{বেগ দূরত্বের সমানুপাতিক}iii. \\text{অতিক্রান্ত সমানুপাতিক দূরত্ব সময়ের বর্গেরনিচের কোনটি সঠিক}?$",
      "image": null,
      "optionA": "$i \\text{ও}ii$",
      "optionA_img": null,
      "optionB": "$i \\text{ও}iii$",
      "optionB_img": null,
      "optionC": "$ii \\text{ও}iii$",
      "optionC_img": null,
      "optionD": "$i, ii \\text{ও}iii$",
      "optionD_img": null,
      "answer": "B",
      "chapter": "2",
      "explanation": "স্থির অবস্থান হতে সুষম ত্বরণ $a$ -এ চলমান বস্তুর জন্য, $v = u + at$, যেখানে $u$ প্রাথমিক বেগ ($u=0$) এবং $v$ চূড়ান্ত বেগ। সুতরাং, $v \\propto t$। $i$ সঠিক।  আবার, $s = ut + \\frac{1}{2}at^2$। যেহেতু $u=0$, তাই $s = \\frac{1}{2}at^2$।  সুতরাং, $s \\propto t^2$। $iii$ সঠিক।  $ii$ ভুল। সুতরাং $i$ ও $iii$ সঠিক, তাই উত্তর B সঠিক।"
    },
    {
      "number": 3,
      "question": "$\\text{তাপবিদ্যুৎ কেন্দ্রের প্রধান উপাদান কোনটি}?$",
      "image": null,
      "optionA": "$\\text{কয়লা}$",
      "optionA_img": null,
      "optionB": "$\\text{খনিজ তেল}$",
      "optionB_img": null,
      "optionC": "$\\text{বাতাস}$",
      "optionC_img": null,
      "optionD": "$\\text{সৌরশক্তি}$",
      "optionD_img": null,
      "answer": "A",
      "chapter": "4",
      "explanation": "তাপবিদ্যুৎ কেন্দ্রে তাপ উৎপন্ন করার জন্য প্রধান উপাদান হিসেবে কয়লা ব্যবহৃত হয়।  কয়লা জ্বালানোর ফলে উৎপন্ন তাপ দিয়ে পানি উত্তপ্ত করা হয় এবং তাপীয় শক্তি বিদ্যুৎ শক্তিতে রূপান্তরিত হয়।"
    },
    {
      "number": 4,
      "question": "$\\text{গাড়িটির ভর}600 kg \\text{হলে উদ্দীপকের}BC \\text{অংশে বাধাপ্রদানকারী বলের মান কত}?$",
      "image": "assets/dFH_eCU9aKfVVjNDpU2VW.png",
      "optionA": "$0 N$",
      "optionA_img": null,
      "optionB": "$100 N$",
      "optionB_img": null,
      "optionC": "$600 N$",
      "optionC_img": null,
      "optionD": "$1200 N$",
      "optionD_img": null,
      "answer": "C",
      "chapter": "3",
      "explanation": "চিত্র থেকে দেখা যাচ্ছে BC অংশে গাড়িটি সমবেগে চলছে। সমবেগে চলমান বস্তুর উপর ক্রিয়াশীল বলের মান শূন্য।  অর্থাৎ, গতির পরিবর্তন হচ্ছে না। নিউটনের প্রথম সূত্র অনুযায়ী, বস্তুর উপর কোনো বল ক্রিয়া না করলে বস্তুটি তার স্থির অবস্থা বা সমবেগে চলমান অবস্থা বজায় রাখে।  BC অংশে গাড়ির ভর 600kg এবং গতি অপরিবর্তিত থাকায় বাধাপ্রদানকারী বলের মান শূন্য নয়। গাড়িটি  সমবেগে চলছে বলে, প্রযুক্ত বল এবং ঘর্ষণ বল সমান ও বিপরীত দিকে। তাই  BC অংশে বাধাপ্রদানকারী বলের মান 600N।"
    },
    {
      "number": 5,
      "question": "$OA \\text{বস্তুটি দর্পণ থেকে}AP \\text{এর দ্বিগুণ দূরত্বে প্রতিবিম্ব সৃষ্টি করলে বিবর্ধনের মান কত}?$",
      "image": "assets/woPl1tOljDePF4MnqbQcK.png",
      "optionA": "$\\frac{1}{4}$",
      "optionA_img": null,
      "optionB": "$\\frac{1}{2}$",
      "optionB_img": null,
      "optionC": "$1$",
      "optionC_img": null,
      "optionD": "$2$",
      "optionD_img": null,
      "answer": "D",
      "chapter": "8",
      "explanation": "প্রশ্নানুসারে, বস্তুর দূরত্ব $u = -2x$  এবং প্রতিবিম্বের দূরত্ব $v = x$।  অতএব,  বিবর্ধন $m = -\\frac{v}{u} = -\\frac{x}{-2x} = \\frac{1}{2}$। উত্তল দর্পণের ক্ষেত্রে, প্রতিবিম্ব আকারের  অনুপাত বস্তুর আকারের সাথে  বিবর্ধন হিসাবে  প্রকাশ করা যায়। প্রশ্নানুসারে, প্রতিবিম্ব  বস্তুর দূরত্বের দ্বিগুণ দূরত্বে  উৎপন্ন হয়।  এটি সম্ভব  যদি  বস্তুটি  ফোকাসের  অর্ধেক দূরত্বে  থাকে।  তাহলে, বিবর্ধন  হবে  $2$।"
    },
    {
      "number": 6,
      "question": "$\\text{স্থির তড়িৎ ব্যবহৃত হয়}-i. \\text{স্প্রে গানে}ii. \\text{ফটোকপিয়ারে}iii. \\text{ইঙ্ক জেট প্রিন্টারেনিচের কোনটি সঠিক}?$",
      "image": null,
      "optionA": "$i \\text{ও}ii$",
      "optionA_img": null,
      "optionB": "$i \\text{ও}iii$",
      "optionB_img": null,
      "optionC": "$ii \\text{ও}iii$",
      "optionC_img": null,
      "optionD": "$i, ii \\text{ও}iii$",
      "optionD_img": null,
      "answer": "D",
      "chapter": "10",
      "explanation": "স্থির তড়িৎ স্প্রে গান, ফটোকপিয়ার এবং ইঙ্ক জেট প্রিন্টারে ব্যবহৃত হয়।  স্থির তড়িৎ এর প্রভাব ব্যবহার করে এগুলো কাজ করে।"
    },
    {
      "number": 7,
      "question": "$\\text{তামার আপেক্ষিক তাপ}400 \\mathrm{Jkg}^{-1} \\mathrm{~K}^{-1} \\text{হলে}5kg \\text{তামার তাপধারণ ক্ষমতা কত}?$",
      "image": null,
      "optionA": "$400 \\mathrm{JK}^{-1}$",
      "optionA_img": null,
      "optionB": "$500 \\mathrm{JK}^{-1}$",
      "optionB_img": null,
      "optionC": "$1000 \\mathrm{JK}^{-1}$",
      "optionC_img": null,
      "optionD": "$2000 \\mathrm{JK}^{-1}$",
      "optionD_img": null,
      "answer": "D",
      "chapter": "6",
      "explanation": "তামার আপেক্ষিক তাপ $c = 400 \\mathrm{Jkg}^{-1} \\mathrm{~K}^{-1}$ এবং ভর $m = 5kg$। তাপধারণ ক্ষমতা $C = mc = 5kg \\times 400 \\mathrm{Jkg}^{-1} \\mathrm{~K}^{-1} = 2000 \\mathrm{JK}^{-1}$"
    },
    {
      "number": 8,
      "question": "$\\text{কোনো বাতির ফিলামেন্টের প্রান্তদ্বয়ের বিভব পার্থক্য}12V \\text{এর রোধ}4 \\Omega \\text{হলে তড়িৎ প্রবাহের মান কত}?$",
      "image": null,
      "optionA": "$3A$",
      "optionA_img": null,
      "optionB": "$4A$",
      "optionB_img": null,
      "optionC": "$8A$",
      "optionC_img": null,
      "optionD": "$10A$",
      "optionD_img": null,
      "answer": "A",
      "chapter": "11",
      "explanation": "ওহমের সূত্র অনুযায়ী, $V = IR$, যেখানে $V$ বিভব পার্থক্য, $I$ তড়িৎ প্রবাহ এবং $R$ রোধ।  প্রশ্নানুসারে, $V = 12V$ এবং $R = 4\\Omega$।  সুতরাং, $I = \\frac{V}{R} = \\frac{12V}{4\\Omega} = 3A$।"
    },
    {
      "number": 9,
      "question": "$50 kg \\text{ভরের এক বালক}7 \\mathrm{~ms}^{-1} \\text{বেগে দৌড়ালে তার গতিশক্তি কত হবে}?$",
      "image": null,
      "optionA": "$350 J$",
      "optionA_img": null,
      "optionB": "$490 J$",
      "optionB_img": null,
      "optionC": "$1225 J$",
      "optionC_img": null,
      "optionD": "$3430 J$",
      "optionD_img": null,
      "answer": "C",
      "chapter": "4",
      "explanation": "গতিশক্তি $KE = \\frac{1}{2}mv^2$, যেখানে $m$ ভর এবং $v$ বেগ। প্রশ্নানুসারে, $m = 50kg$ এবং $v = 7ms^{-1}$।  সুতরাং, $KE = \\frac{1}{2} \\times 50kg \\times (7ms^{-1})^2 = \\frac{1}{2} \\times 50 \\times 49 J = 1225J$।"
    },
    {
      "number": 10,
      "question": "$\\text{কোনো নির্দিষ্ট মাধ্যমে শব্দের কম্পাঙ্ক বৃদ্ধি করলে নিচের কোনটি কমবে}?$",
      "image": null,
      "optionA": "$\\text{তরঙ্গবেগ}$",
      "optionA_img": null,
      "optionB": "$\\text{বিস্তার}$",
      "optionB_img": null,
      "optionC": "$\\text{পর্যায়কাল}$",
      "optionC_img": null,
      "optionD": "$\\text{দশা}$",
      "optionD_img": null,
      "answer": "C",
      "chapter": "7",
      "explanation": "নির্দিষ্ট মাধ্যমে শব্দের বেগ ধ্রুবক।  $v = f\\lambda$, যেখানে $v$ বেগ, $f$ কম্পাঙ্ক এবং $\\lambda$ তরঙ্গদৈর্ঘ্য। কম্পাঙ্ক বৃদ্ধি করলে তরঙ্গদৈর্ঘ্য কমে।  আবার, $T = \\frac{1}{f}$, যেখানে $T$ পর্যায়কাল।  কম্পাঙ্ক বৃদ্ধি করলে পর্যায়কাল কমে।"
    },
    {
      "number": 11,
      "question": "$\\text{কে সর্বপ্রথম ভ্যাকুয়াম টিউব আবিষ্কার করেন}?$",
      "image": null,
      "optionA": "$\\text{এডিসন}$",
      "optionA_img": null,
      "optionB": "$\\text{ফ্লেমিং}$",
      "optionB_img": null,
      "optionC": "$\\text{মার্কনী}$",
      "optionC_img": null,
      "optionD": "$\\text{দ্যা ফরেস্ট}$",
      "optionD_img": null,
      "answer": "B",
      "chapter": "13",
      "explanation": "জন ফ্লেমিং সর্বপ্রথম ভ্যাকুয়াম টিউব আবিষ্কার করেন।"
    },
    {
      "number": 12,
      "question": "$\\text{চিত্রের কোন অংশে গাড়িটি সমবেগে গতিশীল}?$",
      "image": "assets/eMDrHDhB8jipCu_khtGjJ.png",
      "optionA": "$OA \\text{অংশে}$",
      "optionA_img": null,
      "optionB": "$AB \\text{অংশে}$",
      "optionB_img": null,
      "optionC": "$BC \\text{অংশে}$",
      "optionC_img": null,
      "optionD": "$AO \\text{এবং}BC \\text{অংশে}$",
      "optionD_img": null,
      "answer": "B",
      "chapter": "2",
      "explanation": "চিত্রে AB অংশে গাড়ির দূরত্ব সময়ের সাথে সমানুপাতে বৃদ্ধি পাচ্ছে, অর্থাৎ গতিবেগ ধ্রুবক।  সুতরাং AB অংশে গাড়িটি সমবেগে গতিশীল।"
    },
    {
      "number": 13,
      "question": "$\\text{কে পড়ন্ত বস্তুর সূত্রাবলি প্রদান করেন}?$",
      "image": null,
      "optionA": "$\\text{ডঃ গিলবার্ট}$",
      "optionA_img": null,
      "optionB": "$\\text{গ্যালিলিও}$",
      "optionB_img": null,
      "optionC": "$\\text{নিউটন}$",
      "optionC_img": null,
      "optionD": "$\\text{জেমস ওয়াট}$",
      "optionD_img": null,
      "answer": "B",
      "chapter": "2",
      "explanation": "গ্যালিলিও পড়ন্ত বস্তুর সূত্রাবলী প্রদান করেন।"
    },
    {
      "number": 14,
      "question": "$\\text{তামার আয়তন প্রসারণ সহগ কত}?$",
      "image": null,
      "optionA": "$50.1 \\times 10^{-6} \\mathrm{~K}^{-1}$",
      "optionA_img": null,
      "optionB": "$33.4 \\times 10^{-6} \\mathrm{~K}^{-1}$",
      "optionB_img": null,
      "optionC": "$16.7 \\times 10^{-6} \\mathrm{~K}^{-1}$",
      "optionC_img": null,
      "optionD": "$13.7 \\times 10^{-6} \\mathrm{~K}^{-1}$",
      "optionD_img": null,
      "answer": "A",
      "chapter": "6",
      "explanation": "তামার আয়তন প্রসারণ সহগ $\\alpha = 50.1 \\times 10^{-6} K^{-1}$।"
    },
    {
      "number": 15,
      "question": "$\\text{কোনটির আপেক্ষিক রোধের মান সবচেয়ে কম}?$",
      "image": null,
      "optionA": "$\\text{রূপা}$",
      "optionA_img": null,
      "optionB": "$\\text{তামা}$",
      "optionB_img": null,
      "optionC": "$\\text{টাংস্টেন}$",
      "optionC_img": null,
      "optionD": "$\\text{নাইক্রোম}$",
      "optionD_img": null,
      "answer": "A",
      "chapter": "11",
      "explanation": "রূপার আপেক্ষিক রোধের মান সবচেয়ে কম।"
    },
    {
      "number": 16,
      "question": "$OA \\text{লক্ষ্যবস্তুর প্রতিবিম্বের প্রকৃতি কিরূপ}?$",
      "image": "assets/l3wDtBBtIZ4LdgltIO-PC.png",
      "optionA": "$\\text{বাস্তব ও উল্টো}$",
      "optionA_img": null,
      "optionB": "$\\text{অবাস্তব ও খর্বিত}$",
      "optionB_img": null,
      "optionC": "$\\text{অবাস্তব ও বিবর্ধিত}$",
      "optionC_img": null,
      "optionD": "$\\text{অবাস্তব ও উল্টো}$",
      "optionD_img": null,
      "answer": "C",
      "chapter": "8",
      "explanation": "চিত্র থেকে দেখা যায় যে, বস্তুটি অবতল দর্পণের ফোকাসের বাইরে অবস্থিত।  অবতল দর্পণের ফোকাসের বাইরে অবস্থিত বস্তুর প্রতিবিম্ব অবাস্তব ও বিবর্ধিত হয়।"
    },
    {
      "number": 17,
      "question": "$\\text{রক্তাল্পতা রোগের চিকিৎসায় কোনটি ব্যবহৃত হয়}?$",
      "image": null,
      "optionA": "$\\text{কোবাল্ট}-60$",
      "optionA_img": null,
      "optionB": "$\\text{আয়োডিন}-131$",
      "optionB_img": null,
      "optionC": "$\\text{টেকনিশিয়াম}-99m$",
      "optionC_img": null,
      "optionD": "$\\text{ফসফরাস}-32$",
      "optionD_img": null,
      "answer": "D",
      "chapter": "13",
      "explanation": "রক্তাল্পতা রোগের চিকিৎসায় ফসফরাস-32 ব্যবহৃত হয়।"
    },
    {
      "number": 18,
      "question": "$\\text{নিচের কোনটি একটি বিশেষ ছাঁকন যন্ত্র}?$",
      "image": null,
      "optionA": "$\\text{বৃক্ক}$",
      "optionA_img": null,
      "optionB": "$\\text{হৃৎপিণ্ড}$",
      "optionB_img": null,
      "optionC": "$\\text{পাকস্থলী}$",
      "optionC_img": null,
      "optionD": "$\\text{যকৃত}$",
      "optionD_img": null,
      "answer": "A",
      "chapter": "6",
      "explanation": "বৃক্ক একটি বিশেষ ছাঁকন যন্ত্র।"
    },
    {
      "number": 19,
      "question": "$\\text{বাতাসে শব্দের বেগ}340 \\mathrm{~ms}^{-1} \\text{এবং প্রতিধ্বনি শোনার সময়}1.5s \\text{হলে}, \\text{উৎস এবং প্রতিফলক তলের মধ্যবর্তী দূরত্ব কত}?$",
      "image": null,
      "optionA": "$250 m$",
      "optionA_img": null,
      "optionB": "$255 m$",
      "optionB_img": null,
      "optionC": "$260 m$",
      "optionC_img": null,
      "optionD": "$265 m$",
      "optionD_img": null,
      "answer": "B",
      "chapter": "7",
      "explanation": "শব্দের বেগ $v = 340 ms^{-1}$ এবং প্রতিধ্বনি শোনার সময় $t = 1.5s$।  প্রতিধ্বনি শোনার সময় হলো শব্দ যাওয়া ও ফিরে আসার মোট সময়।  সুতরাং, শব্দ যাওয়ার সময় $\\frac{t}{2} = 0.75s$।  দূরত্ব $d = v \\times \\frac{t}{2} = 340 ms^{-1} \\times 0.75s = 255m$।"
    },
    {
      "number": 20,
      "question": "$\\text{প্লাজমা}-i. \\text{পদার্থের চতুর্থ অবস্থা}ii. \\text{কণাগুলো তড়িৎ আধান বহন করে}iii. \\text{কণাগুলোর নির্দিষ্ট আকার ও আয়তন নাইনিচের কোনটি সঠিক}?$",
      "image": null,
      "optionA": "$i \\text{ও}ii$",
      "optionA_img": null,
      "optionB": "$i \\text{ও}iii$",
      "optionB_img": null,
      "optionC": "$ii \\text{ও}iii$",
      "optionC_img": null,
      "optionD": "$i, ii \\text{ও}iii$",
      "optionD_img": null,
      "answer": "D",
      "chapter": "6",
      "explanation": "প্লাজমা পদার্থের চতুর্থ অবস্থা। প্লাজমার কণাগুলো তড়িৎ আধান বহন করে এবং নির্দিষ্ট আকার ও আয়তন নেই।"
    },
    {
      "number": 21,
      "question": "$\\text{সৌরকেন্দ্রিক তত্ত্বের ধারণা প্রদান করেন কে}?$",
      "image": null,
      "optionA": "$\\text{রোমার}$",
      "optionA_img": null,
      "optionB": "$\\text{কোপার্নিকাস}$",
      "optionB_img": null,
      "optionC": "$\\text{ট্রাইকোবাহের}$",
      "optionC_img": null,
      "optionD": "$\\text{কেপলার}$",
      "optionD_img": null,
      "answer": "B",
      "chapter": "2",
      "explanation": "কোপার্নিকাস সৌরকেন্দ্রিক তত্ত্বের ধারণা প্রদান করেন।"
    },
    {
      "number": 22,
      "question": "$\\text{গৌণকুণ্ডলীর তড়িৎপ্রবাহ তিনগুণ করলে মুখ্যকুণ্ডলীর পাকসংখ্যার কী পরিবর্তন হবে}?$",
      "image": "assets/9OI7jUFKmOsB6HNifyy4f.png",
      "optionA": "$\\text{অর্ধেক}$",
      "optionA_img": null,
      "optionB": "$\\text{দ্বিগুণ}$",
      "optionB_img": null,
      "optionC": "$\\text{তিনগুণ}$",
      "optionC_img": null,
      "optionD": "$\\text{ছয়গুণ}$",
      "optionD_img": null,
      "answer": "C",
      "chapter": "12",
      "explanation": "গৌণকুণ্ডলীর তড়িৎপ্রবাহ তিনগুণ করলে মুখ্যকুণ্ডলীর পাকসংখ্যাও তিনগুণ হবে, কারণ প্রেরিত তড়িৎপ্রবাহ  গৌণকুণ্ডলীর পাকসংখ্যা ও মুখ্যকুণ্ডলীর পাকসংখ্যার অনুপাতের উপর নির্ভর করে।"
    },
    {
      "number": 23,
      "question": "$\\text{চিত্রের ক্রান্তিকোণ কোনটি}?$",
      "image": "assets/HUY-qgg8331amcEXQCIzH.png",
      "optionA": "$\\angle \\mathrm{PON}^{\\prime}$",
      "optionA_img": null,
      "optionB": "$\\angle \\mathrm{AOP}$",
      "optionB_img": null,
      "optionC": "$\\angle \\mathrm{AON}$",
      "optionC_img": null,
      "optionD": "$\\angle \\mathrm{BON}$",
      "optionD_img": null,
      "answer": "A",
      "chapter": "9",
      "explanation": "ক্রান্তিকোণ হলো ঘন মাধ্যম থেকে ঝিলিমিলি মাধ্যমে আলোর অপসারণের কোণ যার মান 90°। চিত্রে ক্রান্তিকোণ $\\angle PON^{\\prime}$।"
    },
    {
      "number": 24,
      "question": "$\\text{কোনো স্লাইড ক্যালিপার্সে ভার্নিয়ার ধ্রুবকের মান}0.005 \\text{সে}.\\text{মি}. \\text{হলে ভার্নিয়ার স্কেলের ভাগ সংখ্যা কত}?$",
      "image": null,
      "optionA": "$5$",
      "optionA_img": null,
      "optionB": "$10$",
      "optionB_img": null,
      "optionC": "$15$",
      "optionC_img": null,
      "optionD": "$20$",
      "optionD_img": null,
      "answer": "D",
      "chapter": "1",
      "explanation": "ভার্নিয়ার ধ্রুবক $= \\frac{1}{n}$ মিমি, যেখানে $n$ হল ভার্নিয়ার স্কেলের ভাগ সংখ্যা।  প্রশ্নানুসারে, ভার্নিয়ার ধ্রুবক $0.005$ সে.মি. $= 0.05$ মিমি।  সুতরাং, $\\frac{1}{n} = 0.05$।  অতএব, $n = \\frac{1}{0.05} = 20$।"
    },
    {
      "number": 25,
      "question": "$\\text{অপটিক্যাল ফাইবার পদার্থের প্রতিসরাঙ্ক কত}?$",
      "image": null,
      "optionA": "$1.3$",
      "optionA_img": null,
      "optionB": "$1.5$",
      "optionB_img": null,
      "optionC": "$1.7$",
      "optionC_img": null,
      "optionD": "$2.4$",
      "optionD_img": null,
      "answer": "C",
      "chapter": "9",
      "explanation": "অপটিক্যাল ফাইবার পদার্থের প্রতিসরাঙ্ক $1.7$।"
    }
  ]
}