{
  "board": "MB 24",
  "subject": "islam",
  "questions": [
    {
      "number": 1,
      "question": "$\\text{সাদিয়া সুলতানা তার মেয়েকে ইসলামের একজন মনীষীর কথা বলল}, \\text{তিনি দীর্ঘ ১৬ বছর সাধনা করে ৬ লক্ষ হাদিস থেকে পরীক্ষা}-\\text{নিরীক্ষার মাধ্যমে ৭২৭৫টি হাদিস লিপিবদ্ধ করেন}।\\text{উদ্দীপকে উল্লিখিত মনীষী কে ছিলেন}?$",
      "image": null,
      "optionA": "$\\text{ইমাম বুখারি}(\\text{র})$",
      "optionA_img": null,
      "optionB": "$\\text{আল}-\\text{বিরুনি}$",
      "optionB_img": null,
      "optionC": "$\\text{ইমাম গাযালি}(\\text{র})$",
      "optionC_img": null,
      "optionD": "$\\text{আল}-\\text{কিন্দি}$",
      "optionD_img": null,
      "answer": "A"
    },
    {
      "number": 2,
      "question": "$\\text{জনাব তালহার জমিতে এবার প্রচুর ফসল হওয়ায় তিনি খুশি হয়ে বলেন}, \\text{জমি আমাকে অনেক ফসল দিয়েছে}। \\text{তার এরূপ বক্তব্যে কী প্রতিফলিত হয়েছে}?$",
      "image": null,
      "optionA": "$\\text{কুফর}$",
      "optionA_img": null,
      "optionB": "$\\text{নিফাক}$",
      "optionB_img": null,
      "optionC": "$\\text{ফিস্ক}$",
      "optionC_img": null,
      "optionD": "$\\text{শিরক}$",
      "optionD_img": null,
      "answer": "D"
    },
    {
      "number": 3,
      "question": "$\\text{জনাব}'\\text{ক}' \\text{এক হাজার টাকার নোটের একটি বান্ডিলে দুইটি জাল টাকার নোট ঢুকিয়ে চালিয়ে দিলেন}। \\text{জনাব}'\\text{ক}' \\text{এর কাজটি কীসের শামিল}?$",
      "image": null,
      "optionA": "$\\text{মিথ্যা}$",
      "optionA_img": null,
      "optionB": "$\\text{গিবত}$",
      "optionB_img": null,
      "optionC": "$\\text{হিংসা}$",
      "optionC_img": null,
      "optionD": "$\\text{প্রতারণা}$",
      "optionD_img": null,
      "answer": "D"
    },
    {
      "number": 4,
      "question": "$'\\text{ফিতনা}' \\text{শব্দের অর্থ কী}?$",
      "image": null,
      "optionA": "$\\text{ঘৃণা}$",
      "optionA_img": null,
      "optionB": "$\\text{শত্ৰুতা}$",
      "optionB_img": null,
      "optionC": "$\\text{অরাজকতা}$",
      "optionC_img": null,
      "optionD": "$\\text{ধ্বংস}$",
      "optionD_img": null,
      "answer": "C"
    },
    {
      "number": 5,
      "question": "$\\text{ব্যবসার উদ্দেশ্যে চাচার সংগে যখন সিরিয়ায় যান তখন মহানবি}(\\text{স})-\\text{এর বয়স কত ছিল}?$",
      "image": null,
      "optionA": "$\\text{১০ বছর}$",
      "optionA_img": null,
      "optionB": "$\\text{১১ বছর}$",
      "optionB_img": null,
      "optionC": "$\\text{১২ বছর}$",
      "optionC_img": null,
      "optionD": "$\\text{১৩ বছর}$",
      "optionD_img": null,
      "answer": "C"
    },
    {
      "number": 6,
      "question": "$\\text{জনাব আসাদ সাহেবের নিকট নিসাব পরিমাণের অতিরিক্ত সম্পদ রয়েছে}। \\text{এমতাবস্থায় তার উপর যাকাত আদায় করা}-$",
      "image": null,
      "optionA": "$\\text{সুন্নত}$",
      "optionA_img": null,
      "optionB": "$\\text{ওয়াজিব}$",
      "optionB_img": null,
      "optionC": "$\\text{ফরজ}$",
      "optionC_img": null,
      "optionD": "$\\text{মুস্তাহাব}$",
      "optionD_img": null,
      "answer": "C"
    },
    {
      "number": 7,
      "question": "$\\text{সাওম পালনকারী পানাহার থেকে বিরত থাকে কেন}?$",
      "image": null,
      "optionA": "$\\text{আল্লাহর ভয়ে}$",
      "optionA_img": null,
      "optionB": "$\\text{লোক}-\\text{লজ্জার ভয়ে}$",
      "optionB_img": null,
      "optionC": "$\\text{খাদ্য না থাকায়}$",
      "optionC_img": null,
      "optionD": "$\\text{সম্পদ জমা রাখার জন্য}$",
      "optionD_img": null,
      "answer": "A"
    },
    {
      "number": 8,
      "question": "$“\\text{মায়ের পায়ের তলে সন্তানের বেহেশত}।”— \\text{এটি কার বাণী}?$",
      "image": null,
      "optionA": "$\\text{আল্লাহর}$",
      "optionA_img": null,
      "optionB": "$\\text{সাহাবিদের}$",
      "optionB_img": null,
      "optionC": "$\\text{তাবিঈদের}$",
      "optionC_img": null,
      "optionD": "$\\text{মহানবি}(\\text{স})-\\text{এর}$",
      "optionD_img": null,
      "answer": "D"
    },
    {
      "number": 9,
      "question": "$“\\text{নিশ্চয়ই শিরক চরম জুলুম}।” \\text{কোন সূরার আয়াত}?$",
      "image": null,
      "optionA": "$\\text{আল}-\\text{মায়িদা}$",
      "optionA_img": null,
      "optionB": "$\\text{আন}-\\text{নিসা}$",
      "optionB_img": null,
      "optionC": "$\\text{লুকমান}$",
      "optionC_img": null,
      "optionD": "$\\text{আশ}-\\text{শুরা}$",
      "optionD_img": null,
      "answer": "C"
    },
    {
      "number": 10,
      "question": "$\\text{মামুন কুরআনের শিক্ষা ও উপদেশ অনুধাবন করতে চায়}। \\text{এজন্য তাকে কুরআন পড়তে হবে}-i. \\text{বুঝে}-\\text{শুনে}ii. \\text{চিন্তা}-\\text{গবেষণা করে}iii. \\text{দ্রুততার সাথেনিচের কোনটি সঠিক}?$",
      "image": null,
      "optionA": "$i \\text{ও}ii$",
      "optionA_img": null,
      "optionB": "$i \\text{ও}iii$",
      "optionB_img": null,
      "optionC": "$ii \\text{ও}iii$",
      "optionC_img": null,
      "optionD": "$i, ii \\text{ও}iii$",
      "optionD_img": null,
      "answer": "A"
    },
    {
      "number": 11,
      "question": "$\\text{মহানবি}(\\text{স})-\\text{এর সময় পবিত্র কুরআন সংরক্ষণ করা হয়}-i. \\text{মুখস্থ করার মাধ্যমে}ii. \\text{লিখিতভাবে}iii. \\text{গ্রন্থ আকারেনিচের কোনটি সঠিক}?$",
      "image": null,
      "optionA": "$i \\text{ও}ii$",
      "optionA_img": null,
      "optionB": "$i \\text{ও}iii$",
      "optionB_img": null,
      "optionC": "$ii \\text{ও}iii$",
      "optionC_img": null,
      "optionD": "$i, ii \\text{ও}iii$",
      "optionD_img": null,
      "answer": "A"
    },
    {
      "number": 12,
      "question": "$\\text{জনাব সিদ্দিক আদালতে সাক্ষ্য দিতে যান}। \\text{সত্য সাক্ষ্য দিলে ঝুঁকি আছে জেনেও তিনি মিথ্যা বলেননি}। \\text{তার সাক্ষিতে দুজন নিরপরাধী নিশ্চিত শাস্তি থেকে মুক্তি পান}।\\text{জনাব সিদ্দিকের চরিত্রে কোনটি প্রকাশ পেয়েছে}?$",
      "image": null,
      "optionA": "$\\text{সিদক}$",
      "optionA_img": null,
      "optionB": "$\\text{হিকমা}$",
      "optionB_img": null,
      "optionC": "$\\text{আদল}$",
      "optionC_img": null,
      "optionD": "$\\text{হাসাদ}$",
      "optionD_img": null,
      "answer": "A"
    },
    {
      "number": 13,
      "question": "$\\text{ভিন্ন ভিন্ন রীতিতে কুরআন পাঠে মুসলমানদের মধ্যে ঝগড়ার সূত্রপাত ঘটে}। \\text{বিষয়টি হযরত উসমান}(\\text{রা})-\\text{কে অবহিত করেন কোন সাহাবি}?$",
      "image": null,
      "optionA": "$\\text{যায়িদ ইবনে সাবিত}(\\text{রা})$",
      "optionA_img": null,
      "optionB": "$\\text{হুযায়ফা ইবনে ইয়ামান}(\\text{রা}.)$",
      "optionB_img": null,
      "optionC": "$\\text{আব্দুল্লাহ ইবনে যুবায়ের}(\\text{রা})$",
      "optionC_img": null,
      "optionD": "$\\text{সাঈদ ইবনে আস}(\\text{রা})$",
      "optionD_img": null,
      "answer": "B"
    },
    {
      "number": 14,
      "question": "$\\text{শালীনতা বিরোধী কাজের ফলে}—i. \\text{সমাজে ব্যভিচার ছড়িয়ে পড়ে}ii. \\text{সামাজিক সাম্য বিনষ্ট হয়}iii. \\text{সমাজে অনাচার ছড়িয়ে পড়েনিচের কোনটি সঠিক}?$",
      "image": null,
      "optionA": "$i \\text{ও}ii$",
      "optionA_img": null,
      "optionB": "$i \\text{ও}iii$",
      "optionB_img": null,
      "optionC": "$ii \\text{ও}iii$",
      "optionC_img": null,
      "optionD": "$i, ii \\text{ও}iii$",
      "optionD_img": null,
      "answer": "B"
    },
    {
      "number": 15,
      "question": "$\\text{রিফাত মহান আল্লাহকে এক ও অদ্বিতীয় হিসেবে বিশ্বাস করে}। \\text{সুতরাং সে}-i. \\text{সৎকর্মে উৎসাহিত হবে}ii. \\text{সম্পদশালী হবে}iii. \\text{অশ্লীল কাজ থেকে বিরত থাকবেনিচের কোনটি সঠিক}?$",
      "image": null,
      "optionA": "$i \\text{ও}ii$",
      "optionA_img": null,
      "optionB": "$i \\text{ও}iii$",
      "optionB_img": null,
      "optionC": "$ii \\text{ও}iii$",
      "optionC_img": null,
      "optionD": "$i, ii \\text{ও}iii$",
      "optionD_img": null,
      "answer": "B"
    },
    {
      "number": 16,
      "question": "$\\text{ব্যক্তিত্বসম্পন্ন শিক্ষক সব সময়}-i. \\text{নিয়মনীতি কঠোরভাবে অনুশীলন করেন}ii. \\text{মার্জিত পোশাক পরিধান করেন}iii. \\text{মেধাবী শিক্ষার্থীদের অধিক গুরুত্ব দেননিচের কোনটি সঠিক}?$",
      "image": null,
      "optionA": "$i \\text{ও}ii$",
      "optionA_img": null,
      "optionB": "$i \\text{ও}iii$",
      "optionB_img": null,
      "optionC": "$ii \\text{ও}iii$",
      "optionC_img": null,
      "optionD": "$i, ii \\text{ও}iii$",
      "optionD_img": null,
      "answer": "A"
    },
    {
      "number": 17,
      "question": "$\\text{ইসলামের দৃষ্টিতে জিহাদ কত প্রকার}?$",
      "image": null,
      "optionA": "$\\text{২}$",
      "optionA_img": null,
      "optionB": "$\\text{৩}$",
      "optionB_img": null,
      "optionC": "$\\text{৪}$",
      "optionC_img": null,
      "optionD": "$\\text{৫}$",
      "optionD_img": null,
      "answer": "B"
    },
    {
      "number": 18,
      "question": "$\\text{নাসির উদ্দিন তুসি কত খ্রিষ্টাব্দে জন্মগ্রহণ করেন}?$",
      "image": null,
      "optionA": "$\\text{৯৬৫}$",
      "optionA_img": null,
      "optionB": "$\\text{৭৮০}$",
      "optionB_img": null,
      "optionC": "$\\text{১০৪৮}$",
      "optionC_img": null,
      "optionD": "$\\text{১২০১}$",
      "optionD_img": null,
      "answer": "D"
    },
    {
      "number": 19,
      "question": "$\\text{মুমিনগণের সফলতা ও সম্মানের মূল চাবিকাঠি কী}?$",
      "image": null,
      "optionA": "$\\text{বংশমর্যাদা}$",
      "optionA_img": null,
      "optionB": "$\\text{প্রাচুর্যতা}$",
      "optionB_img": null,
      "optionC": "$\\text{জ্ঞানহীনতা}$",
      "optionC_img": null,
      "optionD": "$\\text{নৈতিকতা}$",
      "optionD_img": null,
      "answer": "D"
    },
    {
      "number": 20,
      "question": "$\\text{জনাব আদনান একজন একনিষ্ঠ মুসলিম হিসাবে জীবনযাপন করতে চান}। \\text{তিনি সিদ্ধান্ত নিয়েছেন অন্যায়}, \\text{অনৈতিক ও অশ্লীল কাজকর্ম করবেন না}। \\text{সর্বাবস্থায় তিনি নীতি}- \\text{নৈতিকতার অনুসরণ করবেনজনাব আদনান কাদের আদর্শে অনুপ্রাণিত হয়ে এমন সিদ্ধান্ত নিয়েছেন}?$",
      "image": null,
      "optionA": "$\\text{সঙ্গি}-\\text{সাথী}$",
      "optionA_img": null,
      "optionB": "$\\text{আলেম}-\\text{উলামা}$",
      "optionB_img": null,
      "optionC": "$\\text{সমাজপতি}$",
      "optionC_img": null,
      "optionD": "$\\text{নবি}-\\text{রাসুল}$",
      "optionD_img": null,
      "answer": "D"
    },
    {
      "number": 21,
      "question": "$\\text{৩০ খানা ছোট কিতাব নাযিল হয়েছিল কোন নবির উপর}?$",
      "image": null,
      "optionA": "$\\text{হযরত ইদ্রিস}(\\text{আ}).$",
      "optionA_img": null,
      "optionB": "$\\text{হযরত ইব্রাহিম}(\\text{আ})$",
      "optionB_img": null,
      "optionC": "$\\text{হযরত শিস}(\\text{আ})$",
      "optionC_img": null,
      "optionD": "$\\text{হযরত আদম}(\\text{আ})$",
      "optionD_img": null,
      "answer": "A"
    },
    {
      "number": 22,
      "question": "$\\text{আল্লাহর পবিত্রতা ও মহিমা ঘোষণা করলে}-i. \\text{আল্লাহ সফলতা দান করবেন}ii. \\text{আল্লাহ সম্পদ দিয়ে দিবেন}iii. \\text{আল্লাহ খুশি হয়ে যাবেননিচের কোনটি সঠিক}?$",
      "image": null,
      "optionA": "$i \\text{ও}ii$",
      "optionA_img": null,
      "optionB": "$i \\text{ও}iii$",
      "optionB_img": null,
      "optionC": "$ii \\text{ও}iii$",
      "optionC_img": null,
      "optionD": "$i, ii \\text{ও}iii$",
      "optionD_img": null,
      "answer": "B"
    },
    {
      "number": 23,
      "question": "$\\text{শরিয়তের উৎসসমূহ কয়টি}?$",
      "image": null,
      "optionA": "$\\text{২}$",
      "optionA_img": null,
      "optionB": "$\\text{৩}$",
      "optionB_img": null,
      "optionC": "$\\text{৪}$",
      "optionC_img": null,
      "optionD": "$\\text{৫}$",
      "optionD_img": null,
      "answer": "C"
    },
    {
      "number": 24,
      "question": "$“\\text{যে ব্যক্তি মনোযোগসহ সালাত আদায় করে}, \\text{কিয়ামতের দিন ঐ সালাত তার জন্য নুর হবে}।”- \\text{হাদিসটি কোন গ্রন্থে বর্ণিত হয়েছে}?$",
      "image": null,
      "optionA": "$\\text{তিরমিযি}$",
      "optionA_img": null,
      "optionB": "$\\text{বুখারি}$",
      "optionB_img": null,
      "optionC": "$\\text{মুসলিম}$",
      "optionC_img": null,
      "optionD": "$\\text{তাবারানি}$",
      "optionD_img": null,
      "answer": "D"
    },
    {
      "number": 25,
      "question": "$\\text{জনাব আদনান একজন একনিষ্ঠ মুসলিম হিসাবে জীবনযাপন করতে চান}। \\text{তিনি সিদ্ধান্ত নিয়েছেন অন্যায়}, \\text{অনৈতিক ও অশ্লীল কাজকর্ম করবেন না}। \\text{সর্বাবস্থায় তিনি নীতি}- \\text{নৈতিকতার অনুসরণ করবেনজনাব আদনানের সিদ্ধান্ত বাস্তবায়িত হলে তিনি}-i. \\text{শ্রেষ্ঠ আলেমের মর্যাদা পাবেন}ii. \\text{নৈতিক আচরণে উদ্বুদ্ধ হবেন}iii. \\text{উত্তম চরিত্রের নমুনা হবেননিচের কোনটি সঠিক}?$",
      "image": null,
      "optionA": "$i \\text{ও}ii$",
      "optionA_img": null,
      "optionB": "$i \\text{ও}iii$",
      "optionB_img": null,
      "optionC": "$ii \\text{ও}iii$",
      "optionC_img": null,
      "optionD": "$i, ii \\text{ও}iii$",
      "optionD_img": null,
      "answer": "C"
    },
    {
      "number": 26,
      "question": "$\\text{সাদিয়া সুলতানা তার মেয়েকে ইসলামের একজন মনীষীর কথা বলল}, \\text{তিনি দীর্ঘ ১৬ বছর সাধনা করে ৬ লক্ষ হাদিস থেকে পরীক্ষা}-\\text{নিরীক্ষার মাধ্যমে ৭২৭৫টি হাদিস লিপিবদ্ধ করেন}।\\text{উদ্দীপকে উল্লিখিত মনীষী যে গুণাবলির অধিকারী ছিলেন}—i. \\text{অহংকারী}ii. \\text{আত্মসম্মানবোধ সম্পন্ন}iii. \\text{স্বাধীনচেতানিচের কোনটি সঠিক}?$",
      "image": null,
      "optionA": "$i \\text{ও}ii$",
      "optionA_img": null,
      "optionB": "$i \\text{ও}iii$",
      "optionB_img": null,
      "optionC": "$ii \\text{ও}iii$",
      "optionC_img": null,
      "optionD": "$i, ii \\text{ও}iii$",
      "optionD_img": null,
      "answer": "C"
    },
    {
      "number": 27,
      "question": "$\\text{বাল্যকাল থেকে জ্ঞানের প্রতি প্রবল আগ্রহ ছিল কার}?$",
      "image": null,
      "optionA": "$\\text{ইমাম বুখারি}(\\text{র})$",
      "optionA_img": null,
      "optionB": "$\\text{ইমাম আবু হানিফা}(\\text{র})$",
      "optionB_img": null,
      "optionC": "$\\text{ইমাম গাযালি}(\\text{র})$",
      "optionC_img": null,
      "optionD": "$\\text{ইবনে জারির তাবারি}(\\text{র})$",
      "optionD_img": null,
      "answer": "A"
    },
    {
      "number": 28,
      "question": "$\\text{জনাব সিদ্দিক আদালতে সাক্ষ্য দিতে যান}। \\text{সত্য সাক্ষ্য দিলে ঝুঁকি আছে জেনেও তিনি মিথ্যা বলেননি}। \\text{তার সাক্ষিতে দুজন নিরপরাধী নিশ্চিত শাস্তি থেকে মুক্তি পান}।\\text{এর ফলে তিনি}—i. \\text{পূণ্য লাভ করবেন}ii. \\text{জান্নাত লাভ করবেন}iii. \\text{সম্পদশালী হতে পারবেননিচের কোনটি সঠিক}?$",
      "image": null,
      "optionA": "$i \\text{ও}ii$",
      "optionA_img": null,
      "optionB": "$i \\text{ও}iii$",
      "optionB_img": null,
      "optionC": "$ii \\text{ও}iii$",
      "optionC_img": null,
      "optionD": "$i, ii \\text{ও}iii$",
      "optionD_img": null,
      "answer": "A"
    },
    {
      "number": 29,
      "question": "$\\text{দেশের কল্যাণে আমাদের উচিত}- i. \\text{স্বাধীনতা রক্ষায় কাজ করা}ii. \\text{জাতীয় উন্নতিতে অবদান রাখা}iii. \\text{সম্পদের অপচয় করা নিচের কোনটি সঠিক}?$",
      "image": null,
      "optionA": "$i \\text{ও}ii$",
      "optionA_img": null,
      "optionB": "$i \\text{ও}iii$",
      "optionB_img": null,
      "optionC": "$ii \\text{ও}iii$",
      "optionC_img": null,
      "optionD": "$i, ii \\text{ও}iii$",
      "optionD_img": null,
      "answer": "A"
    },
    {
      "number": 30,
      "question": "$“\\text{চরম মিথ্যাবাদী}” \\text{এর আরবি প্রতিশব্দ কী}?$",
      "image": null,
      "optionA": "$\\text{কায্যাব}$",
      "optionA_img": null,
      "optionB": "$\\text{কাযিব}$",
      "optionB_img": null,
      "optionC": "$\\text{সাদিক}$",
      "optionC_img": null,
      "optionD": "$\\text{সিদ্দিক}$",
      "optionD_img": null,
      "answer": "A"
    }
  ]
}