{
  "board": "RB 23",
  "subject": "bgs",
  "questions": [
    {
      "number": 1,
      "question": "$\\text{কে}. \\text{সি}. \\text{কলেজের বিজ্ঞান বিভাগের ২য় বর্ষের ছাত্রী শিলা মামার বাসায় বেড়াতে ঢাকায় আসে}। \\text{পাশের বাসার একটি ছেলে শিলাকে দেখে বাজে ইঙ্গিত করে}।\\text{উক্ত সমস্যা সমাধানে করণীয়}-i. \\text{ধর্মীয় মূল্যবোধ ও আদর্শ চর্চা করা}ii. \\text{সামাজিক চাপ প্রয়োগকারী প্রতিষ্ঠানকে সক্রিয় করা}iii. \\text{অপরাধীকে সামাজিকভাবে বয়কট করানিচের কোনটি সঠিক}?$",
      "image": null,
      "optionA": "$i \\text{ও}ii$",
      "optionA_img": null,
      "optionB": "$i \\text{ও}ii$",
      "optionB_img": null,
      "optionC": "$ii \\text{ও}iii$",
      "optionC_img": null,
      "optionD": "$i, ii \\text{ও}iii$",
      "optionD_img": null,
      "answer": "D"
    },
    {
      "number": 2,
      "question": "$\\text{যমুনার উপনদী হলো}-$",
      "image": null,
      "optionA": "$\\text{করতোয়া ও আত্রাই}$",
      "optionA_img": null,
      "optionB": "$\\text{ধরলা ও তিস্তা}$",
      "optionB_img": null,
      "optionC": "$\\text{বুড়িগঙ্গা ও গোমতী}$",
      "optionC_img": null,
      "optionD": "$\\text{ধলেশ্বরী ও হালদা}$",
      "optionD_img": null,
      "answer": "A"
    },
    {
      "number": 3,
      "question": "$\\text{উৎপাদন প্রক্রিয়ায় উৎপাদিত উপাদানকে কী বলে}?$",
      "image": null,
      "optionA": "$\\text{সংগঠন}$",
      "optionA_img": null,
      "optionB": "$\\text{বণ্টন}$",
      "optionB_img": null,
      "optionC": "$\\text{মূলধন}$",
      "optionC_img": null,
      "optionD": "$\\text{শ্রম}$",
      "optionD_img": null,
      "answer": "C"
    },
    {
      "number": 4,
      "question": "$\\text{মি}. \\text{হ্যানয় রোহিঙ্গা সমস্যা সমাধানে একটি আন্তর্জাতিক সংস্থার প্রতিনিধি হিসাবে ঢাকায় কর্মরত আছেন}। \\text{তিনি মিয়ানমার সামরিক জান্তা এবং বাংলাদেশের পররাষ্ট্র মন্ত্রণালয়ের সাথে রোহিঙ্গা ইস্যুতে মধ্যস্থতা করছেন}।\\text{মি}. \\text{হ্যানয় আন্তর্জাতিক কোন সংস্থার সাথে সম্পৃক্ত}?$",
      "image": null,
      "optionA": "$UNDP$",
      "optionA_img": null,
      "optionB": "$UNHCR$",
      "optionB_img": null,
      "optionC": "$UNIFEM$",
      "optionC_img": null,
      "optionD": "$UNESCO$",
      "optionD_img": null,
      "answer": "B"
    },
    {
      "number": 5,
      "question": "$\\text{সাধুহাটী বাজারের পাশে}'\\text{গড়াই}' \\text{বেড়িবাঁধ প্রতিবছর সংস্কার করা হলেও}, \\text{অনেক স্থানে বড় বড় ভাঙন দেখা দেয়}। \\text{ফলে জনজীবনে দুর্দশা নেমে আসে}। \\text{অথচ সরকার প্রতি বছর এই বাঁধ মেরামতে প্রচুর অর্থ ব্যয় করে}।\\text{উদ্দীপকে কোন সামাজিক সমস্যাটি ফুটে উঠেছে}?$",
      "image": null,
      "optionA": "$\\text{সড়ক দুর্ঘটনা}$",
      "optionA_img": null,
      "optionB": "$\\text{নৈরাজ্য}$",
      "optionB_img": null,
      "optionC": "$\\text{দুর্নীতি}$",
      "optionC_img": null,
      "optionD": "$\\text{দরিদ্রতা}$",
      "optionD_img": null,
      "answer": "C"
    },
    {
      "number": 6,
      "question": "$\\text{মুজিবনগর সরকারের}\"\\text{পররাষ্ট্র ও আইনমন্ত্রী}\" \\text{কে ছিলেন}?$",
      "image": null,
      "optionA": "$\\text{এম মনসুর আলী}$",
      "optionA_img": null,
      "optionB": "$\\text{তাজউদ্দীন আহমদ}$",
      "optionB_img": null,
      "optionC": "$\\text{এ এইচ এম কামারুজ্জামান}$",
      "optionC_img": null,
      "optionD": "$\\text{খন্দকার মোশতাক আহমদ}$",
      "optionD_img": null,
      "answer": "D"
    },
    {
      "number": 7,
      "question": "$\\text{প্রথম বিশ্বযুদ্ধের পর বিশ্বশান্তি প্রতিষ্ঠার লক্ষ্যে গঠিত হয়}-$",
      "image": null,
      "optionA": "$\\text{লীগ অফ নেশনস}$",
      "optionA_img": null,
      "optionB": "$\\text{জাতিসংঘ}$",
      "optionB_img": null,
      "optionC": "$\\text{ইউনেস্কো}$",
      "optionC_img": null,
      "optionD": "$\\text{ইউনিসেফ}$",
      "optionD_img": null,
      "answer": "A"
    },
    {
      "number": 8,
      "question": "$See the question in the image.$",
      "image": "assets/do-MBNaN91LulJ8XS4-4D.png",
      "optionA": "$\\text{সঞ্চয়}$",
      "optionA_img": null,
      "optionB": "$\\text{বিনিয়োগ}$",
      "optionB_img": null,
      "optionC": "$\\text{উপযোগ}$",
      "optionC_img": null,
      "optionD": "$\\text{উৎপাদন}$",
      "optionD_img": null,
      "answer": "D"
    },
    {
      "number": 9,
      "question": "$\\text{একটি নদী ভারত থেকে রাজশাহী জেলার মধ্য দিয়ে বাংলাদেশে প্রবেশ করেছে}। \\text{উক্ত নদী ভারত ও বাংলাদেশে ভিন্ন ভিন্ন নামে পরিচিত}। \\text{নদীটির নাম কী}?$",
      "image": null,
      "optionA": "$\\text{যমুনা}$",
      "optionA_img": null,
      "optionB": "$\\text{তিস্তা}$",
      "optionB_img": null,
      "optionC": "$\\text{মেঘনা}$",
      "optionC_img": null,
      "optionD": "$\\text{পদ্মা}$",
      "optionD_img": null,
      "answer": "D"
    },
    {
      "number": 10,
      "question": "$\\text{পাঁচশালা পরিকল্পনার জন্য বঙ্গবন্ধু সরকার}-i. \\text{পঞ্চম বার্ষিক পরিকল্পনা কমিশন গঠন করেন}ii. \\text{বিভিন্ন দল নিয়ে বাকশাল গঠন}iii. \\text{সুদসহ কৃষি জমির খাজনা মওকুফ করেননিচের কোনটি সঠিক}?$",
      "image": null,
      "optionA": "$i \\text{ও}ii$",
      "optionA_img": null,
      "optionB": "$i \\text{ও}iii$",
      "optionB_img": null,
      "optionC": "$ii \\text{ও}iii$",
      "optionC_img": null,
      "optionD": "$i, ii \\text{ও}iii$",
      "optionD_img": null,
      "answer": "B"
    },
    {
      "number": 11,
      "question": "$\\text{রাষ্ট্রের উপাদান কয়টি}?$",
      "image": null,
      "optionA": "$\\text{৩}$",
      "optionA_img": null,
      "optionB": "$\\text{৪}$",
      "optionB_img": null,
      "optionC": "$\\text{৫}$",
      "optionC_img": null,
      "optionD": "$\\text{৬}$",
      "optionD_img": null,
      "answer": "B"
    },
    {
      "number": 12,
      "question": "$\\text{৮ম শ্রেণির শিক্ষার্থী হামজা দেশের উত্তর}-\\text{পূর্বাঞ্চলে বেড়াতে দিয়ে কোন পাহাড়টি দেখতে পাবে}?$",
      "image": null,
      "optionA": "$\\text{বিজয়}$",
      "optionA_img": null,
      "optionB": "$\\text{হিমালয়}$",
      "optionB_img": null,
      "optionC": "$\\text{চিকনাগুল}$",
      "optionC_img": null,
      "optionD": "$\\text{আরাকান}$",
      "optionD_img": null,
      "answer": "C"
    },
    {
      "number": 13,
      "question": "$\\text{আধুনিক রাষ্ট্রে আইনের প্রধান উৎস কোনটি}?$",
      "image": null,
      "optionA": "$\\text{প্রথা}$",
      "optionA_img": null,
      "optionB": "$\\text{ধর্ম}$",
      "optionB_img": null,
      "optionC": "$\\text{ন্যায়বোধ}$",
      "optionC_img": null,
      "optionD": "$\\text{আইনসভা}$",
      "optionD_img": null,
      "answer": "D"
    },
    {
      "number": 14,
      "question": "$\\text{সম্প্রতি ব্যস্ততম একটি রাস্তার ধারে যাত্রী ছাউনি নির্মাণ করা হয়েছে}। \\text{আসা যাওয়ার পথে পথিকগণ এখানে বিশ্রাম নেন}। \\text{এই নির্মাণকৃত বিষয়টি কোন ধরনের সম্পদ}?$",
      "image": null,
      "optionA": "$\\text{ব্যক্তিগত}$",
      "optionA_img": null,
      "optionB": "$\\text{একান্ত ব্যক্তিগত}$",
      "optionB_img": null,
      "optionC": "$\\text{সমষ্টিগত}$",
      "optionC_img": null,
      "optionD": "$\\text{জাতীয়}$",
      "optionD_img": null,
      "answer": "C"
    },
    {
      "number": 15,
      "question": "$\\text{কে}. \\text{সি}. \\text{কলেজের বিজ্ঞান বিভাগের ২য় বর্ষের ছাত্রী শিলা মামার বাসায় বেড়াতে ঢাকায় আসে}। \\text{পাশের বাসার একটি ছেলে শিলাকে দেখে বাজে ইঙ্গিত করে}।\\text{শিলা কোন সামাজিক সমস্যার শিকার}?$",
      "image": null,
      "optionA": "$\\text{ছিনতাই}$",
      "optionA_img": null,
      "optionB": "$\\text{কিশোর অপরাধ}$",
      "optionB_img": null,
      "optionC": "$\\text{ইভটিজিং}$",
      "optionC_img": null,
      "optionD": "$\\text{রাহাজানি}$",
      "optionD_img": null,
      "answer": "C"
    },
    {
      "number": 16,
      "question": "$\\text{যুক্তফ্রন্ট সরকারকে বরখাস্ত করেন কে}?$",
      "image": null,
      "optionA": "$\\text{গোলাম মোহাম্মদ}$",
      "optionA_img": null,
      "optionB": "$\\text{আইয়ুব খান}$",
      "optionB_img": null,
      "optionC": "$\\text{ইস্কান্দার মীর্জা}$",
      "optionC_img": null,
      "optionD": "$\\text{ইয়াহিয়া খান}$",
      "optionD_img": null,
      "answer": "A"
    },
    {
      "number": 17,
      "question": "$\\text{এরশাদ বিরোধী আন্দোলন শুরু করে প্রথম}-$",
      "image": null,
      "optionA": "$\\text{নুর হোসেন}$",
      "optionA_img": null,
      "optionB": "$\\text{১৫ দলীয় ঐক্যজোট}$",
      "optionB_img": null,
      "optionC": "$\\text{৭ দলীয় জোট}$",
      "optionC_img": null,
      "optionD": "$\\text{ছাত্র সমাজ}$",
      "optionD_img": null,
      "answer": "D"
    },
    {
      "number": 18,
      "question": "$\\text{তমদ্দুন মজলিস মূলত একটি}-$",
      "image": null,
      "optionA": "$\\text{রাজনৈতিক প্রতিষ্ঠান}$",
      "optionA_img": null,
      "optionB": "$\\text{সাংস্কৃতিক সংগঠন}$",
      "optionB_img": null,
      "optionC": "$\\text{সামাজিক সংস্থা}$",
      "optionC_img": null,
      "optionD": "$\\text{অর্থনৈতিক কমিটি}$",
      "optionD_img": null,
      "answer": "B"
    },
    {
      "number": 19,
      "question": "$\\text{অতি অল্প সময়ে মিত্র বাহিনীকে ভারতে ফেরত}, \\text{শিক্ষা কমিশন গঠন এবং সংবিধান প্রণয়নসহ অন্যান্য কাজকে বঙ্গবন্ধুর কোন কাজের সাথে তুলনা করা যায়}?$",
      "image": null,
      "optionA": "$\\text{দেশ পুনর্গঠন}$",
      "optionA_img": null,
      "optionB": "$\\text{দ্বিতীয় বিপ্লব}$",
      "optionB_img": null,
      "optionC": "$\\text{পাঁচশালা পরিকল্পনা}$",
      "optionC_img": null,
      "optionD": "$\\text{অবকাঠামোগত উন্নতি}$",
      "optionD_img": null,
      "answer": "A"
    },
    {
      "number": 20,
      "question": "$'\\text{স্মৃতির মিনার}' \\text{কে রচনা করেন}?$",
      "image": null,
      "optionA": "$\\text{ইমদাদুল হক}$",
      "optionA_img": null,
      "optionB": "$\\text{মাহবুবল আলম}$",
      "optionB_img": null,
      "optionC": "$\\text{আলাউদ্দিন আল আজাদ}$",
      "optionC_img": null,
      "optionD": "$\\text{ডঃ এনামুল হক}$",
      "optionD_img": null,
      "answer": "C"
    },
    {
      "number": 21,
      "question": "$\\text{পৃথিবীর কোন দেশকে}MDG \\text{অর্জনের রোল মডেল বলা হয়েছে}?$",
      "image": null,
      "optionA": "$\\text{চীন}$",
      "optionA_img": null,
      "optionB": "$\\text{জাপান}$",
      "optionB_img": null,
      "optionC": "$\\text{ভারত}$",
      "optionC_img": null,
      "optionD": "$\\text{বাংলাদেশ}$",
      "optionD_img": null,
      "answer": "D"
    },
    {
      "number": 22,
      "question": "$\\text{অভ্যন্তরীণ নৌ পরিবহন কর্তপক্ষকে বলা হয়}-$",
      "image": null,
      "optionA": "$BIWRT$",
      "optionA_img": null,
      "optionB": "$BIWTA$",
      "optionB_img": null,
      "optionC": "$BIWPN$",
      "optionC_img": null,
      "optionD": "$BIWNA$",
      "optionD_img": null,
      "answer": "B"
    },
    {
      "number": 23,
      "question": "$\\text{টারশিয়ারি যুগের পাহাড় আছে}-$",
      "image": null,
      "optionA": "$\\text{নেত্রকোনায়}$",
      "optionA_img": null,
      "optionB": "$\\text{বরিশালে}$",
      "optionB_img": null,
      "optionC": "$\\text{যশোরে}$",
      "optionC_img": null,
      "optionD": "$\\text{রাজশাহীতে}$",
      "optionD_img": null,
      "answer": "A"
    },
    {
      "number": 24,
      "question": "$\\text{আইনের প্রাধান্য বজায় থাকলে}-i. \\text{সরকার স্বেচ্ছাচারী হতে পারে না}ii. \\text{সকলের জন্য একই আইন প্রযোজ্য হয়}iii. \\text{নাগরিকের স্বাধীনতার রক্ষা করা হয় নিচের কোনটি সঠিক}?$",
      "image": null,
      "optionA": "$i \\text{ও}ii$",
      "optionA_img": null,
      "optionB": "$i \\text{ও}iii$",
      "optionB_img": null,
      "optionC": "$ii \\text{ও}iii$",
      "optionC_img": null,
      "optionD": "$i, ii \\text{ও}iii$",
      "optionD_img": null,
      "answer": "D"
    },
    {
      "number": 25,
      "question": "$\\text{সাধুহাটী বাজারের পাশে}'\\text{গড়াই}' \\text{বেড়িবাঁধ প্রতিবছর সংস্কার করা হলেও}, \\text{অনেক স্থানে বড় বড় ভাঙন দেখা দেয়}। \\text{ফলে জনজীবনে দুর্দশা নেমে আসে}। \\text{অথচ সরকার প্রতি বছর এই বাঁধ মেরামতে প্রচুর অর্থ ব্যয় করে}।\\text{উক্ত সমস্যা সমাধানে দরকার}-i. \\text{বাজেট বৃদ্ধি করা}ii. \\text{দোষীদের বিচার করা}iii. \\text{জবাবদিহিতা প্রতিষ্ঠা করানিচের কোনটি সঠিক}?$",
      "image": null,
      "optionA": "$i \\text{ও}ii$",
      "optionA_img": null,
      "optionB": "$i \\text{ও}iii$",
      "optionB_img": null,
      "optionC": "$ii \\text{ও}iii$",
      "optionC_img": null,
      "optionD": "$i, ii \\text{ও}iii$",
      "optionD_img": null,
      "answer": "C"
    },
    {
      "number": 26,
      "question": "$\\text{কোন মৌসুমী বায়ুর প্রভাবে বাংলাদেশে বর্ষাকালে প্রচুর বৃষ্টিপাত হয়}?$",
      "image": null,
      "optionA": "$\\text{দক্ষিণ}-\\text{পশ্চিম}$",
      "optionA_img": null,
      "optionB": "$\\text{উত্তর}-\\text{পশ্চিম}$",
      "optionB_img": null,
      "optionC": "$\\text{দক্ষিণ}-\\text{পূর্ব}$",
      "optionC_img": null,
      "optionD": "$\\text{উত্তর}-\\text{পূর্ব}$",
      "optionD_img": null,
      "answer": "A"
    },
    {
      "number": 27,
      "question": "$\\text{মি}. \\text{হ্যানয় রোহিঙ্গা সমস্যা সমাধানে একটি আন্তর্জাতিক সংস্থার প্রতিনিধি হিসাবে ঢাকায় কর্মরত আছেন}। \\text{তিনি মিয়ানমার সামরিক জান্তা এবং বাংলাদেশের পররাষ্ট্র মন্ত্রণালয়ের সাথে রোহিঙ্গা ইস্যুতে মধ্যস্থতা করছেন}।\\text{উক্ত সংস্থা বাংলাদেশে আরো যে বিষয়ে অবদান রাখছে তা হলো}-i. \\text{বিশাল শরণার্থীর ব্যয় নির্বাহ}ii. \\text{কৃষকদের কৃষি বিষয়ক পরামর্শ দান}iii. \\text{বিহারী জনগোষ্ঠীর আবাসন প্রদাননিচের কোনটি সঠিক}?$",
      "image": null,
      "optionA": "$i \\text{ও}ii$",
      "optionA_img": null,
      "optionB": "$i \\text{ও}iii$",
      "optionB_img": null,
      "optionC": "$ii \\text{ও}iii$",
      "optionC_img": null,
      "optionD": "$i, ii \\text{ও}iii$",
      "optionD_img": null,
      "answer": "B"
    },
    {
      "number": 28,
      "question": "$\\text{সাইফুল এন্ড সন্স কোম্পানি বছর শেষে ২},\\text{০০},\\text{০০০ লভ্যাংশ পান}। \\text{এর মধ্যে জমি ব্যবহার বাবদ মালিককে ৫},\\text{০০০ টাকা দিতে হয়}। \\text{উক্ত ৫},\\text{০০০ টাকাকে অর্থনীতির ভাষায় কী বলে}?$",
      "image": null,
      "optionA": "$\\text{খাজনা}$",
      "optionA_img": null,
      "optionB": "$\\text{মজুরি}$",
      "optionB_img": null,
      "optionC": "$\\text{সুদ}$",
      "optionC_img": null,
      "optionD": "$\\text{মুনাফা}$",
      "optionD_img": null,
      "answer": "A"
    },
    {
      "number": 29,
      "question": "$SDG \\text{বাস্তবায়নে জরুরি হলো}-$",
      "image": null,
      "optionA": "$\\text{বৈদেশিক বাণিজ্যের উন্নয়ন}$",
      "optionA_img": null,
      "optionB": "$\\text{বৈষম্য সহনীয় পর্যায়ে নামিয়ে আনা}$",
      "optionB_img": null,
      "optionC": "$\\text{দরিদ্র দেশকে সহায়তা করা}$",
      "optionC_img": null,
      "optionD": "$\\text{জলবায়ু পরিবর্তন রোধ করা}$",
      "optionD_img": null,
      "answer": "B"
    },
    {
      "number": 30,
      "question": "$\\text{কোন নদীর শাখা নদী বেশি}?$",
      "image": null,
      "optionA": "$\\text{কর্ণফুলী}$",
      "optionA_img": null,
      "optionB": "$\\text{ব্রহ্মপুত্র}$",
      "optionB_img": null,
      "optionC": "$\\text{পদ্মা}$",
      "optionC_img": null,
      "optionD": "$\\text{যমুনা}$",
      "optionD_img": null,
      "answer": "C"
    }
  ]
}