{
  "board": "BB 25",
  "subject": "biology",
  "questions": [
    {
      "number": 1,
      "question": "$\\text{স্বয়ংক্রিয় স্নায়ু নেই নিচের কোন অঙ্গে}?$",
      "image": null,
      "optionA": "$\\text{হৃৎপিণ্ড}$",
      "optionA_img": null,
      "optionB": "$\\text{পাকস্থলী}$",
      "optionB_img": null,
      "optionC": "$\\text{জিহ্বা}$",
      "optionC_img": null,
      "optionD": "$\\text{অগ্ন্যাশয়}$",
      "optionD_img": null,
      "answer": "C",
      "chapter": "10",
      "explanation": "প্রশ্নে জিজ্ঞাসা করা হয়েছে যে কোন অঙ্গে স্বয়ংক্রিয় স্নায়ু নেই। স্বয়ংক্রিয় স্নায়ুতন্ত্র হৃৎপিণ্ড, পাকস্থলী ও অগ্ন্যাশয়ের কার্যক্রম নিয়ন্ত্রণ করে। কিন্তু জিহ্বার কার্যক্রম ইচ্ছানুসারে নিয়ন্ত্রিত হয়, যার জন্য সোমেটিক স্নায়ুতন্ত্র দায়ী।  সুতরাং, জিহ্বায় স্বয়ংক্রিয় স্নায়ু নেই।  সঠিক উত্তর C।"
    },
    {
      "number": 2,
      "question": "$A \\text{ও}B \\text{উভয়ই}i. \\text{পানি ও খনিজ পদার্থ পরিবহণ করে}ii. \\text{উদ্ভিদে দৃঢ়তা প্রদান করে}iii. \\text{শর্করা পরিবহণ করেনিচের কোনটি সঠিক}?$",
      "image": "assets/3Bag5czShEm9N8f7Bolio.png",
      "optionA": "$i \\text{ও}ii$",
      "optionA_img": null,
      "optionB": "$i \\text{ও}iii$",
      "optionB_img": null,
      "optionC": "$ii \\text{ও}iii$",
      "optionC_img": null,
      "optionD": "$i, ii \\text{ও}iii$",
      "optionD_img": null,
      "answer": "A",
      "chapter": "2",
      "explanation": "প্রশ্নে A ও B দুটি উদ্ভিদের কাঠামোর কথা বলা হয়েছে, যা পানি ও খনিজ লবণ পরিবহণ করে এবং উদ্ভিদকে দৃঢ়তা প্রদান করে। এটি স্পষ্টতই জাইলেম এবং ফ্লোয়েমকে বোঝায়। জাইলেম পানি এবং খনিজ লবণ পরিবহণ করে এবং উদ্ভিদে দৃঢ়তা প্রদান করে। ফ্লোয়েম শর্করা পরিবহণ করে।  সুতরাং, শুধুমাত্র i ও ii সঠিক।  সঠিক উত্তর A।"
    },
    {
      "number": 3,
      "question": "$\\text{মাশরুমের কোষপ্রাচীর কী দ্বারা গঠিত}?$",
      "image": null,
      "optionA": "$\\text{লিপিড}$",
      "optionA_img": null,
      "optionB": "$\\text{লিগনিন}$",
      "optionB_img": null,
      "optionC": "$\\text{পেকটিন}$",
      "optionC_img": null,
      "optionD": "$\\text{কাইটিন}$",
      "optionD_img": null,
      "answer": "D",
      "chapter": "2",
      "explanation": "মাশরুম একটি ছত্রাক। ছত্রাকের কোষপ্রাচীর কাইটিন দিয়ে গঠিত।  সঠিক উত্তর D।"
    },
    {
      "number": 4,
      "question": "$A \\text{এর কোষগুলো}-i. \\text{পরিণত বয়সে মৃত}ii. \\text{চোঙের মতো}iii. \\text{কয়েক সে}.\\text{মি}. \\text{লম্বানিচের কোনটি সঠিক}?$",
      "image": "assets/yW3Erviq_it4GaZwKgwh6.png",
      "optionA": "$i \\text{ও}ii$",
      "optionA_img": null,
      "optionB": "$i \\text{ও}iii$",
      "optionB_img": null,
      "optionC": "$ii \\text{ও}iii$",
      "optionC_img": null,
      "optionD": "$i, ii \\text{ও}iii$",
      "optionD_img": null,
      "answer": "D",
      "chapter": "2",
      "explanation": "প্রশ্নে A হলো জাইলেম। জাইলেমের কোষগুলো পরিণত বয়সে মৃত, চোঙাকৃতি এবং কয়েক সেন্টিমিটার লম্বা হয়।  সঠিক উত্তর D।"
    },
    {
      "number": 5,
      "question": "$\\text{ট্রানজিশনাল টিস্যু কোনটি}?$",
      "image": null,
      "optionA": "$\\text{মেরুদন্ডী প্রাণীর শ্বাসনালী}$",
      "optionA_img": null,
      "optionB": "$\\text{হাইড্রার এন্ড্রোডার্ম}$",
      "optionB_img": null,
      "optionC": "$\\text{মেরুদন্ডী প্রাণীর ত্বক}$",
      "optionC_img": null,
      "optionD": "$\\text{বৃক্কের সংগ্রাহক নালী}$",
      "optionD_img": null,
      "answer": "C",
      "chapter": "2",
      "explanation": "ট্রানজিশনাল টিস্যু হলো এক ধরণের আবরণী টিস্যু যা মেরুদন্ডী প্রাণীদের ত্বকে পাওয়া যায়। এটি  বহুস্তরীয় এবং প্রসারণশীল।  সঠিক উত্তর C।"
    },
    {
      "number": 6,
      "question": "$\\text{নিচের কোনটি ধনাত্মক আন্তঃক্রিয়া}?$",
      "image": null,
      "optionA": "$\\text{মিউচুয়ালিজম}$",
      "optionA_img": null,
      "optionB": "$\\text{শোষণ}$",
      "optionB_img": null,
      "optionC": "$\\text{প্রতিযোগিতা}$",
      "optionC_img": null,
      "optionD": "$\\text{অ্যান্টিবায়োসিস}$",
      "optionD_img": null,
      "answer": "A",
      "chapter": "13",
      "explanation": "মিউচুয়ালিজম হলো দুটি জীবের মধ্যে এমন একটি ধনাত্মক আন্তঃক্রিয়া যেখানে উভয়ই উপকৃত হয়।  সঠিক উত্তর A।"
    },
    {
      "number": 7,
      "question": "$\\text{চিত্রের}P \\text{চিহ্নিত অংশে কোন আবরণী টিস্যু দেখা যায়}?$",
      "image": "assets/TLZlKJOpusmXyal-yMJHB.png",
      "optionA": "$\\text{সাধারণ}$",
      "optionA_img": null,
      "optionB": "$\\text{স্কোয়ামাশ}$",
      "optionB_img": null,
      "optionC": "$\\text{স্ট্র্যাটিফাইড}$",
      "optionC_img": null,
      "optionD": "$\\text{সিউডো}-\\text{স্ট্র্যাটিফাইড}$",
      "optionD_img": null,
      "answer": "D",
      "chapter": "2",
      "explanation": "চিত্রটিতে  সিউডো-স্ট্র্যাটিফাইড  আবরণী টিস্যু দেখানো হয়েছে।  সঠিক উত্তর D।"
    },
    {
      "number": 8,
      "question": "$\\text{পনস্ এর আকৃতি কেমন}?$",
      "image": null,
      "optionA": "$\\text{গোলাকৃতি}$",
      "optionA_img": null,
      "optionB": "$\\text{নলাকৃতি}$",
      "optionB_img": null,
      "optionC": "$\\text{ডিম্বাকৃতি}$",
      "optionC_img": null,
      "optionD": "$\\text{ত্রিভুজাকৃতি}$",
      "optionD_img": null,
      "answer": "B",
      "chapter": "6",
      "explanation": "পনস্  নলাকৃতি।  সঠিক উত্তর B।"
    },
    {
      "number": 9,
      "question": "$\\text{প্রায় কত ঘণ্টা পর নিষিক্ত ডিম্বাণুর কোষ বিভাজন শুরু}-\\text{হয়}?$",
      "image": null,
      "optionA": "$\\text{১৮}$",
      "optionA_img": null,
      "optionB": "$\\text{২৪}$",
      "optionB_img": null,
      "optionC": "$\\text{৩৬}$",
      "optionC_img": null,
      "optionD": "$\\text{৭২}$",
      "optionD_img": null,
      "answer": "C",
      "chapter": "11",
      "explanation": "নিষিক্ত ডিম্বাণুর কোষ বিভাজন প্রায় ৩৬ ঘণ্টা পর শুরু হয়।  সঠিক উত্তর C।"
    },
    {
      "number": 10,
      "question": "$\\text{কিডনিতে পাথর হওয়ার কারণ কোনটি}?$",
      "image": null,
      "optionA": "$\\text{ঔষধের পার্শ্বপ্রতিক্রিয়া}$",
      "optionA_img": null,
      "optionB": "$\\text{অতিরিক্ত রক্তক্ষরণ}$",
      "optionB_img": null,
      "optionC": "$\\text{অতিরিক্ত শারীরিক ওজন}$",
      "optionC_img": null,
      "optionD": "$\\text{মারাত্মক ডায়রিয়া}$",
      "optionD_img": null,
      "answer": "C",
      "chapter": "8",
      "explanation": "কিডনিতে পাথর হওয়ার একটি প্রধান কারণ হল অতিরিক্ত শারীরিক ওজন।  সঠিক উত্তর C।"
    },
    {
      "number": 11,
      "question": "$\\text{কোনো বাক্তির}BMI \\text{যদি ২৯}.\\text{৯}-\\text{হয়}, \\text{তিনি}BMI \\text{মানদণ্ডের কোন অবস্থানে থাকবেন}?$",
      "image": null,
      "optionA": "$\\text{সুস্বাস্থোয় আদর্শ মান}$",
      "optionA_img": null,
      "optionB": "$\\text{শরীরের অতিরিক্ত ওজন}$",
      "optionB_img": null,
      "optionC": "$\\text{মোটা হওয়ার প্রথম স্তর}$",
      "optionC_img": null,
      "optionD": "$\\text{মোটা হওয়ার দ্বিতীয় স্তর}$",
      "optionD_img": null,
      "answer": "B",
      "chapter": "5",
      "explanation": "BMI 29.9  শারীরিক অতিরিক্ত ওজনকে নির্দেশ করে।  সঠিক উত্তর B।"
    },
    {
      "number": 12,
      "question": "$\\text{নিচের কোনটি কেবল মাত্র}RNA \\text{তে পাওয়া যায়}?$",
      "image": null,
      "optionA": "$\\text{ইউরাসিল}$",
      "optionA_img": null,
      "optionB": "$\\text{এডেনিন}$",
      "optionB_img": null,
      "optionC": "$\\text{গুয়ানিন}$",
      "optionC_img": null,
      "optionD": "$\\text{সাইটোসিন}$",
      "optionD_img": null,
      "answer": "A",
      "chapter": "12",
      "explanation": "ইউরাসিল কেবলমাত্র RNA তে পাওয়া যায়, DNA তে নয়।  সঠিক উত্তর A।"
    },
    {
      "number": 13,
      "question": "$\\text{১০০ গ্রাম মুড়িয়ে কত কিলোক্যালরি শক্তি পাওয়া যায়}?$",
      "image": null,
      "optionA": "$\\text{১০০}$",
      "optionA_img": null,
      "optionB": "$\\text{২০০}$",
      "optionB_img": null,
      "optionC": "$\\text{৩০০}$",
      "optionC_img": null,
      "optionD": "$\\text{৪০০}$",
      "optionD_img": null,
      "answer": "D",
      "chapter": "5",
      "explanation": "১০০ গ্রাম মুড়িতে প্রায় ৪০০ কিলোক্যালরি শক্তি থাকে।  সঠিক উত্তর D।"
    },
    {
      "number": 14,
      "question": "$\\text{বেরিয়াম এক্স}-\\text{রে এর মাধ্যমে কোন রোগ নির্ণয় করা হয়}?$",
      "image": null,
      "optionA": "$\\text{অ্যাপেনডিসাইটিস}$",
      "optionA_img": null,
      "optionB": "$\\text{অজীর্ণতা}$",
      "optionB_img": null,
      "optionC": "$\\text{পেপটিক আলসার}$",
      "optionC_img": null,
      "optionD": "$\\text{কোষ্ঠকাঠিন্য}$",
      "optionD_img": null,
      "answer": "C",
      "chapter": "5",
      "explanation": "বেরিয়াম এক্স-রে  পেপটিক আলসার নির্ণয়ে ব্যবহৃত হয়।  সঠিক উত্তর C।"
    },
    {
      "number": 15,
      "question": "$\\text{চিত্রের}M \\text{চিহ্নিত অংশ}-i. \\text{অ্যাস্টার রে তৈরি করে}ii. \\text{বিভিন্ন ধরনের ফ্ল্যাজেলা তৈরি করে}iii. \\text{কিছু হরমোন নিঃসরণ করেনিচের কোনটি সঠিক}?$",
      "image": "assets/PB0QR8Br3iRHylGsHOeUE.png",
      "optionA": "$i \\text{ও}ii$",
      "optionA_img": null,
      "optionB": "$i \\text{ও}iii$",
      "optionB_img": null,
      "optionC": "$ii \\text{ও}iii$",
      "optionC_img": null,
      "optionD": "$i, ii \\text{ও}iii$",
      "optionD_img": null,
      "answer": "A",
      "chapter": "2",
      "explanation": "চিত্রের M চিহ্নিত অংশ গল্গি বডি। গল্গি বডি অ্যাস্টার রে তৈরি করে এবং বিভিন্ন ধরনের ফ্ল্যাজেলা তৈরিতে সাহায্য করে।  সঠিক উত্তর A।"
    },
    {
      "number": 16,
      "question": "$\\text{পরিবেশ সুরক্ষায় ব্যবহৃত হয় কোনটি}?$",
      "image": null,
      "optionA": "$Entamoeba$",
      "optionA_img": null,
      "optionB": "$Shigella$",
      "optionB_img": null,
      "optionC": "$Helicobactar$",
      "optionC_img": null,
      "optionD": "$Pseudomonas$",
      "optionD_img": null,
      "answer": "D",
      "chapter": "13",
      "explanation": "পরিবেশ সুরক্ষায়  Pseudomonas ব্যবহৃত হয়।  সঠিক উত্তর D।"
    },
    {
      "number": 17,
      "question": "$\\text{কোন গ্রন্থি শিশুকালে বিকশিত থাকে পরে বয়োবৃদ্ধির সাথে সাথে ছোট হয়ে যায়}?$",
      "image": null,
      "optionA": "$\\text{থাইরয়েড}$",
      "optionA_img": null,
      "optionB": "$\\text{প্যারাথাইরয়েড}$",
      "optionB_img": null,
      "optionC": "$\\text{থাইমাস}$",
      "optionC_img": null,
      "optionD": "$\\text{অ্যাডরেনাল}$",
      "optionD_img": null,
      "answer": "C",
      "chapter": "10",
      "explanation": "থাইমাস গ্রন্থি শিশুকালে বিকশিত থাকে এবং বয়োবৃদ্ধির সাথে সাথে ছোট হয়ে যায়।  সঠিক উত্তর C।"
    },
    {
      "number": 18,
      "question": "$Y \\text{এবং}Z \\text{উভয়ই}-$",
      "image": "assets/F570_L02e5dXF4GzzPiZ9.png",
      "optionA": "$\\text{হিস্টামিন নিঃসৃত করে}$",
      "optionA_img": null,
      "optionB": "$\\text{জীবাণু ভক্ষণ করে}$",
      "optionB_img": null,
      "optionC": "$\\text{এন্টিবডি তৈরি করে}$",
      "optionC_img": null,
      "optionD": "$\\text{রক্ত জমাট বাঁধতে সাহায্য করে}$",
      "optionD_img": null,
      "answer": "A",
      "chapter": "10",
      "explanation": "চিত্রে Y এবং Z হলো মাস্ট সেল। মাস্ট সেল হিস্টামিন নিঃসরণ করে।  সঠিক উত্তর A।"
    },
    {
      "number": 19,
      "question": "$\\text{চিত্র}X \\text{এর ক্ষেত্রে প্রয়োজ}।i. \\text{লাল অস্থিমজ্জায় তৈরি হয়}?ii. \\text{দ্বি}-\\text{অবতল বৃত্তের মত}iii. \\text{হিমোগ্লোবিন বিদ্যমাননিচের কোনটি সঠিক}?$",
      "image": "assets/DRqQwD5QqaBDvwrKI6L0k.png",
      "optionA": "$i \\text{ও}ii$",
      "optionA_img": null,
      "optionB": "$i \\text{ও}iii$",
      "optionB_img": null,
      "optionC": "$ii \\text{ও}iii$",
      "optionC_img": null,
      "optionD": "$i, ii \\text{ও}iii$",
      "optionD_img": null,
      "answer": "D",
      "chapter": "6",
      "explanation": "চিত্র X হলো রক্তকণিকা (RBC)। RBC লাল অস্থিমজ্জায় তৈরি হয়, দ্বি-অবতল বৃত্তাকার এবং হিমোগ্লোবিন ধারণ করে।  সঠিক উত্তর D।"
    },
    {
      "number": 20,
      "question": "$\\text{গোনান্ড থাকে}i. \\text{ডিম্বাশয়ে}ii. \\text{শুক্রাশয়ে}iii. \\text{বৃক্কের উপরেনিচের কোনটি সঠিকা}$",
      "image": null,
      "optionA": "$i \\text{ও}ii$",
      "optionA_img": null,
      "optionB": "$i \\text{ও}iii$",
      "optionB_img": null,
      "optionC": "$ii \\text{ও}iii$",
      "optionC_img": null,
      "optionD": "$i, ii \\text{ও}iii$",
      "optionD_img": null,
      "answer": "A",
      "chapter": "11",
      "explanation": "গোনান্ড ডিম্বাশয় এবং শুক্রাশয় উভয়তেই অবস্থান করে।  সঠিক উত্তর A।"
    },
    {
      "number": 21,
      "question": "$\\text{নিচের কোনটি ঝিল্লী বিহীন সাইটোপ্লাজমীয় অঙ্গাণু}?$",
      "image": null,
      "optionA": "$\\text{লাইসোজোম}$",
      "optionA_img": null,
      "optionB": "$\\text{রাইবোজোম}$",
      "optionB_img": null,
      "optionC": "$\\text{মাইটোকন্ড্রিয়া}$",
      "optionC_img": null,
      "optionD": "$\\text{প্লাস্টিড}$",
      "optionD_img": null,
      "answer": "B",
      "chapter": "2",
      "explanation": "রাইবোজোম ঝিল্লী বিহীন সাইটোপ্লাজমীয় অঙ্গাণু।  সঠিক উত্তর B।"
    },
    {
      "number": 22,
      "question": "$\\text{পুংকেশর দলমন্ডলের সাথে যুক্ত থাকে কোন ফুলে}?$",
      "image": null,
      "optionA": "$\\text{ধুতুরা}$",
      "optionA_img": null,
      "optionB": "$\\text{জবা}$",
      "optionB_img": null,
      "optionC": "$\\text{শিমুল}$",
      "optionC_img": null,
      "optionD": "$\\text{কদম}$",
      "optionD_img": null,
      "answer": "A",
      "chapter": "11",
      "explanation": "পুংকেশর দলমন্ডল ধুতুরার ফুলে পুষ্পদলে যুক্ত থাকে।  সঠিক উত্তর A।"
    },
    {
      "number": 23,
      "question": "$\\text{উদ্ভিদের ফটোট্রপিক চলনে কোন হরমোন সাহায্য করে}?$",
      "image": null,
      "optionA": "$\\text{অক্সিন}$",
      "optionA_img": null,
      "optionB": "$\\text{জিবেরেলিন}$",
      "optionB_img": null,
      "optionC": "$\\text{সাইটোকাইনিন}$",
      "optionC_img": null,
      "optionD": "$\\text{ভার্নালিন}$",
      "optionD_img": null,
      "answer": "A",
      "chapter": "10",
      "explanation": "অক্সিন উদ্ভিদের ফটোট্রপিক চলনে সাহায্য করে।  সঠিক উত্তর A।"
    },
    {
      "number": 24,
      "question": "$\\text{সালোকসংশ্লেষণের বাহ্যিক প্রভাবক কোনটি}?$",
      "image": null,
      "optionA": "$\\text{ক্লোরোফিদ}$",
      "optionA_img": null,
      "optionB": "$\\text{আলো}$",
      "optionB_img": null,
      "optionC": "$\\text{পটাসিয়ায়}$",
      "optionC_img": null,
      "optionD": "$\\text{এনজাইম}$",
      "optionD_img": null,
      "answer": "B",
      "chapter": "4",
      "explanation": "আলো সালোকসংশ্লেষণের একটি বাহ্যিক প্রভাবক।  সঠিক উত্তর B।"
    },
    {
      "number": 25,
      "question": "$\\text{উদ্ভিদের প্রোটিনের পাঠনিক উপাদান কোনটি}?$",
      "image": null,
      "optionA": "$B$",
      "optionA_img": null,
      "optionB": "$Mg$",
      "optionB_img": null,
      "optionC": "$S$",
      "optionC_img": null,
      "optionD": "$K$",
      "optionD_img": null,
      "answer": "C",
      "chapter": "4",
      "explanation": "সালফার ($S$) উদ্ভিদের প্রোটিনের পাঠনিক উপাদান।  সঠিক উত্তর C।"
    }
  ]
}