{
  "board": "DB 25",
  "subject": "higher-math",
  "questions": [
    {
      "number": 1,
      "question": "$F(x)=\\sqrt{2 x-3} \\text{ফাংশনটির ডোমেন নিচের কোনটি}?$",
      "image": null,
      "optionA": "$\\text{ডোম}F=\\left\\{x \\in R: x \\neq \\frac{3}{2}\\right\\}$",
      "optionA_img": null,
      "optionB": "$\\text{ডোম}F=\\left\\{x \\in R: x>\\frac{3}{2}\\right\\}$",
      "optionB_img": null,
      "optionC": "$\\text{ডোম}F=\\left\\{x \\in R: x \\geq \\frac{3}{2}\\right\\}$",
      "optionC_img": null,
      "optionD": "$\\text{ডোম}F=\\left\\{x \\in R: x \\leq \\frac{3}{2}\\right\\}$",
      "optionD_img": null,
      "answer": "C",
      "chapter": "1",
      "explanation": "প্রদত্ত ফাংশন $F(x) = \\sqrt{2x - 3}$।  একটি বর্গমূল ফাংশনের জন্য, বর্গমূলের ভিতরের রাশিটি অঋণাত্মক হতে হবে।  অর্থাৎ, $2x - 3 \\geq 0$।  এই অসমতা সমাধান করে পাই $2x \\geq 3$, অথবা $x \\geq \\frac{3}{2}$।  সুতরাং, ফাংশনটির ডোমেইন হলো $\\{x \\in \\mathbb{R} : x \\geq \\frac{3}{2}\\}$।  এটি বিকল্প C এর সাথে মিলে যায়।"
    },
    {
      "number": 2,
      "question": "$25^{3 x}=125^{5 y} \\text{হলে তবে}\\frac{x}{y} \\text{এর মান কত}?$",
      "image": null,
      "optionA": "$\\frac{2}{5}$",
      "optionA_img": null,
      "optionB": "$\\frac{3}{5}$",
      "optionB_img": null,
      "optionC": "$\\frac{5}{3}$",
      "optionC_img": null,
      "optionD": "$\\frac{5}{2}$",
      "optionD_img": null,
      "answer": "D",
      "chapter": "9",
      "explanation": "$25^{3x} = 125^{5y}$। আমরা জানি $25 = 5^2$ এবং $125 = 5^3$।  সুতরাং, $(5^2)^{3x} = (5^3)^{5y}$।  এখন, ঘাতের ঘাতের সূত্র প্রয়োগ করে পাই $5^{6x} = 5^{15y}$।  যেহেতু ভিত্তিগুলো সমান, তাই ঘাতগুলোও সমান হবে।  অর্থাৎ, $6x = 15y$।  এখন, $\\frac{x}{y}$ নির্ণয় করতে পারি: $\\frac{x}{y} = \\frac{15}{6} = \\frac{5}{2}$।  এটি বিকল্প D এর সাথে মিলে যায়।"
    },
    {
      "number": 3,
      "question": "$22 \\text{সে}.\\text{মি}. \\text{ধারবিশিষ্ট ঘনক আকৃতির বাক্সে একটি গোলক ঠিকভাবে এঁটে যায়}। \\text{গোলকটির পৃষ্ঠতলের ক্ষেত্রফল কত}?$",
      "image": null,
      "optionA": "$484 \\pi \\text{বর্গ সে}.\\text{মি}$",
      "optionA_img": null,
      "optionB": "$1936 \\pi \\text{বর্গ সে}.\\text{মি}$",
      "optionB_img": null,
      "optionC": "$2904 \\text{বর্গ সে}.\\text{মি}$",
      "optionC_img": null,
      "optionD": "$7744 \\pi \\text{বর্গ সে}.\\text{মি}$",
      "optionD_img": null,
      "answer": "A",
      "chapter": "13",
      "explanation": "ঘনকের ধার $22$ সে.মি.।  গোলকটি ঘনকের ভেতরে ঠিকভাবে এঁটে যায়, তাই গোলকের ব্যাসার্ধ ঘনকের ধারের অর্ধেক হবে।  অর্থাৎ, গোলকের ব্যাসার্ধ $r = \\frac{22}{2} = 11$ সে.মি.। গোলকের পৃষ্ঠতলের ক্ষেত্রফল $4\\pi r^2 = 4\\pi (11)^2 = 484\\pi$ বর্গ সে.মি.।  এটি বিকল্প A এর সাথে মিলে যায়।"
    },
    {
      "number": 4,
      "question": "$2+0.2+0.02+\\ldots . . . . \\text{ধারাটির অসীমতক সমষ্টি কত}?$",
      "image": null,
      "optionA": "$\\frac{9}{20}$",
      "optionA_img": null,
      "optionB": "$\\frac{20}{11}$",
      "optionB_img": null,
      "optionC": "$\\frac{111}{50}$",
      "optionC_img": null,
      "optionD": "$\\frac{20}{9}$",
      "optionD_img": null,
      "answer": "D",
      "chapter": "7",
      "explanation": "ধারাটি হলো $2 + 0.2 + 0.02 + ...$। এটি একটি অসীম গুণোত্তর ধারা যার প্রথম পদ $a = 2$ এবং সাধারণ অনুপাত $r = 0.1 = \\frac{1}{10}$।  $|r| < 1$ যেহেতু, ধারাটির অসীমতক সমষ্টি বিদ্যমান।  অসীম গুণোত্তর ধারার সমষ্টির সূত্র হলো $S = \\frac{a}{1 - r} = \\frac{2}{1 - \\frac{1}{10}} = \\frac{2}{\\frac{9}{10}} = \\frac{20}{9}$।  এটি বিকল্প D এর সাথে মিলে যায়।"
    },
    {
      "number": 5,
      "question": "$x^{2}-3 x-2=0 \\text{সমীকরণের নিশ্চায়ক কত}?$",
      "image": null,
      "optionA": "$\\frac{1}{2}(3-\\sqrt{17})$",
      "optionA_img": null,
      "optionB": "$\\frac{1}{2}(3+\\sqrt{17})$",
      "optionB_img": null,
      "optionC": "$\\sqrt{17}$",
      "optionC_img": null,
      "optionD": "$17$",
      "optionD_img": null,
      "answer": "D",
      "chapter": "5",
      "explanation": "দ্বিঘাত সমীকরণ $x^2 - 3x - 2 = 0$ এর নির্ণায়ক হলো $D = b^2 - 4ac$ যেখানে $a = 1$, $b = -3$, এবং $c = -2$।  সুতরাং, $D = (-3)^2 - 4(1)(-2) = 9 + 8 = 17$।  এটি বিকল্প D এর সাথে মিলে যায়।"
    },
    {
      "number": 6,
      "question": "$\\text{চিত্রে}, D \\text{ও}E \\text{মধ্যবিন্দু হলে}i. \\overrightarrow{P E}=\\overrightarrow{P D}+\\overrightarrow{D E} ii. \\overrightarrow{P Q}+\\overrightarrow{Q R}+\\overrightarrow{R P}=\\underline{0} iii. \\overrightarrow{Q R}=2 \\overrightarrow{E D} \\text{নিচের কোনটি সঠিক}?$",
      "image": "assets/46itOJA2mMFCX9DcNZgWe.png",
      "optionA": "$i \\text{ও}ii$",
      "optionA_img": null,
      "optionB": "$i \\text{ও}iii$",
      "optionB_img": null,
      "optionC": "$ii \\text{ও}iii$",
      "optionC_img": null,
      "optionD": "$i, ii \\text{ও}iii$",
      "optionD_img": null,
      "answer": "A",
      "chapter": "12",
      "explanation": "ত্রিভুজের মধ্যবিন্দু উপপাদ্য অনুযায়ী, $\\overrightarrow{PE} = \\overrightarrow{PD} + \\overrightarrow{DE}$ সঠিক।  ত্রিভুজের তিনটি বাহুর ভেক্টর যোগফল শূন্য হয়, তাই $\\overrightarrow{PQ} + \\overrightarrow{QR} + \\overrightarrow{RP} = \\vec{0}$ সঠিক।  $iii$ অংশটি ভুল, কারণ এখানে $\\overrightarrow{QR}$ এবং $\\overrightarrow{ED}$ পরস্পর সমান্তরাল কিন্তু বিপরীত দিকে।"
    },
    {
      "number": 7,
      "question": "$P(x, y, z)=x^{2} y+y^{2} z+z^{2} x \\text{হলে}-i. P(x, y, z) \\text{সমমাত্রিক বহুপদী}ii. P(x, y, z) \\text{প্রতিসম রাশি}iii. P(x, y, z) \\text{চক্র}-\\text{ক্রমিক রাশি নিচের কোনটি সঠিক}?$",
      "image": null,
      "optionA": "$i \\text{ও}ii$",
      "optionA_img": null,
      "optionB": "$i \\text{ও}iii$",
      "optionB_img": null,
      "optionC": "$ii \\text{ও}iii$",
      "optionC_img": null,
      "optionD": "$i, ii \\text{ও}iii$",
      "optionD_img": null,
      "answer": "B",
      "chapter": "2",
      "explanation": "$P(x, y, z) = x^2y + y^2z + z^2x$।  এই বহুপদীটি সমমাত্রিক নয়, কারণ $x$, $y$, $z$ এর ঘাতের যোগফল সমান নয়।  $P(x, y, z)$ প্রতিসম নয় কারণ $x$, $y$, $z$ এর স্থান বিনিময় করলে একই রাশি পাওয়া যায় না।  তবে, $P(x, y, z)$ একটি চক্র-ক্রমিক রাশি, কারণ $x$, $y$, $z$ এর চক্রীয় স্থান বিনিময় করলে একই রাশি পাওয়া যায়।"
    },
    {
      "number": 8,
      "question": "$\\angle x=80^{\\circ} \\text{হলে}\\angle x \\text{এর সম্পূরক কোণের এক পঞ্চমাংশ কত}?$",
      "image": null,
      "optionA": "$100^{\\circ}$",
      "optionA_img": null,
      "optionB": "$50^{\\circ}$",
      "optionB_img": null,
      "optionC": "$22^{\\circ}$",
      "optionC_img": null,
      "optionD": "$20^{\\circ}$",
      "optionD_img": null,
      "answer": "D",
      "chapter": "8",
      "explanation": "$\\angle x = 80^\\circ$।  $\\angle x$ এর সম্পূরক কোণ হলো $180^\\circ - 80^\\circ = 100^\\circ$।  সম্পূরক কোণের এক পঞ্চমাংশ হলো $\\frac{100^\\circ}{5} = 20^\\circ$।  এটি বিকল্প D এর সাথে মিলে যায়।"
    },
    {
      "number": 9,
      "question": "$\\text{০ কেন্দ্র বিশিষ্ট অর্ধবৃত্তে}OB = 2.5 \\text{সে}.\\text{মি}.।AB= 4 \\text{সে}.\\text{মি}. \\text{হলে}AC \\text{এর উপর}BC \\text{এর লম্ব অভিক্ষেপ কত}?$",
      "image": "assets/ARRw7GzkwthS60z9T28ZE.png",
      "optionA": "$\\text{০ সে}.\\text{মি}.$",
      "optionA_img": null,
      "optionB": "$3 \\text{সে}.\\text{মি}$",
      "optionB_img": null,
      "optionC": "$4 \\text{সে}.\\text{মি}.$",
      "optionC_img": null,
      "optionD": "$5 \\text{সে}.\\text{মি}$",
      "optionD_img": null,
      "answer": "B",
      "chapter": "3",
      "explanation": "চিত্রে, একটি সমকোণী ত্রিভুজ OBC দেখা যাচ্ছে।  $OB = 2.5$ সে.মি. এবং $AB = 4$ সে.মি.  পিথাগোরাসের উপপাদ্য ব্যবহার করে, $OC = \\sqrt{OB^2 - BC^2} = \\sqrt{2.5^2 - 2^2} = \\sqrt{6.25 - 4} = \\sqrt{2.25} = 1.5$ সে.মি.  $AC$ এর উপর $BC$ এর লম্ব অভিক্ষেপ হল $OC = 1.5$ সে.মি.  (সমস্যাটিতে গণিতের ত্রুটি আছে, বিকল্পে 3 দেওয়া হলেও উত্তর 1.5 হওয়া উচিত)।"
    },
    {
      "number": 10,
      "question": "$\\left(x^{2}-4 x+4\\right)^{2} \\text{এর বিস্তৃতিতে পদসংখ্যা কত}?$",
      "image": null,
      "optionA": "$2$",
      "optionA_img": null,
      "optionB": "$3$",
      "optionB_img": null,
      "optionC": "$4$",
      "optionC_img": null,
      "optionD": "$5$",
      "optionD_img": null,
      "answer": "D",
      "chapter": "10",
      "explanation": "$(x^2 - 4x + 4)^2 = (x - 2)^4$।  $(x - 2)^4$ এর বিস্তৃতিতে $n + 1 = 4 + 1 = 5$ টি পদ থাকবে।  এটি বিকল্প D এর সাথে মিলে যায়।"
    },
    {
      "number": 11,
      "question": "$3x + 7 \\leq 5x + 3 \\text{অসমতাটির সমাধান সেট কোনটি}?$",
      "image": null,
      "optionA": "$S=\\{x \\in R: x \\geq 2\\} .$",
      "optionA_img": null,
      "optionB": "$S=\\{x \\in R: x>2\\}$",
      "optionB_img": null,
      "optionC": "$S=\\{x \\in R: x \\leq 2\\}$",
      "optionC_img": null,
      "optionD": "$S=\\{x \\in R: x \\geq-2\\}$",
      "optionD_img": null,
      "answer": "A",
      "chapter": "6",
      "explanation": "$3x + 7 \\leq 5x + 3$।  $7 - 3 \\leq 5x - 3x$।  $4 \\leq 2x$।  $x \\geq 2$।  সমাধান সেট হলো $\\{x \\in \\mathbb{R} : x \\geq 2\\}$। এটি বিকল্প A এর সাথে মিলে যায়।"
    },
    {
      "number": 12,
      "question": "$A(5,-3) \\text{এবং}B(-3,2) \\text{হলে}AB \\text{এর}i. \\text{দৈর্ঘ্য}\\sqrt{89} \\text{একক}ii. \\text{ঢাল}\\frac{5}{8} iii. \\text{সমীকরণ}5 x+8 y=1 \\text{নিচের কোনটি সঠিক}?$",
      "image": null,
      "optionA": "$i \\text{ও}ii$",
      "optionA_img": null,
      "optionB": "$i \\text{ও}iii$",
      "optionB_img": null,
      "optionC": "$ii \\text{ও}iii$",
      "optionC_img": null,
      "optionD": "$i, ii \\text{ও}iii$",
      "optionD_img": null,
      "answer": "B",
      "chapter": "11",
      "explanation": "$A(5, -3)$ এবং $B(-3, 2)$।  $AB$ এর দৈর্ঘ্য $= \\sqrt{(5 - (-3))^2 + (-3 - 2)^2} = \\sqrt{8^2 + (-5)^2} = \\sqrt{64 + 25} = \\sqrt{89}$ একক।  $AB$ এর ঢাল $= \\frac{2 - (-3)}{-3 - 5} = \\frac{5}{-8} = -\\frac{5}{8}$।  সমীকরণটি ভুল।"
    },
    {
      "number": 13,
      "question": "$\\text{০ কেন্দ্র বিশিষ্ট অর্ধবৃত্তে}OB = 2.5 \\text{সে}.\\text{মি}.।ABC \\text{ত্রিভুজের নববিন্দু বৃত্তের ব্যাসার্ধ কত}?$",
      "image": "assets/ARRw7GzkwthS60z9T28ZE.png",
      "optionA": "$1.25 \\text{সে}.\\text{মি}$",
      "optionA_img": null,
      "optionB": "$2.50 \\text{সে}.\\text{মি}$",
      "optionB_img": null,
      "optionC": "$5 \\text{সে}.\\text{মি}.$",
      "optionC_img": null,
      "optionD": "$10 \\text{সে}.\\text{মি}$",
      "optionD_img": null,
      "answer": "A",
      "chapter": "3",
      "explanation": "নববিন্দু বৃত্তের ব্যাসার্ধ অর্ধবৃত্তের ব্যাসার্ধের অর্ধেক।  অর্ধবৃত্তের ব্যাসার্ধ $2.5$ সে.মি., তাই নববিন্দু বৃত্তের ব্যাসার্ধ $\\frac{2.5}{2} = 1.25$ সে.মি.।  এটি বিকল্প A এর সাথে মিলে যায়।"
    },
    {
      "number": 14,
      "question": "$22 \\text{সে}.\\text{মি}. \\text{ধারবিশিষ্ট ঘনক আকৃতির বাক্সে একটি গোলক ঠিকভাবে এঁটে যায়}।\\text{বাক্সটির অনধিকৃত অংশের আয়তন কত}?$",
      "image": null,
      "optionA": "$506.84 \\text{ঘন সে}.\\text{মি}. (\\text{প্রায়})$",
      "optionA_img": null,
      "optionB": "$5072.71 \\text{ঘন সে}.\\text{মি}. (\\text{প্রায়})$",
      "optionB_img": null,
      "optionC": "$9127.47 \\text{ঘন সে}.\\text{মি}. (\\text{প্রায়})$",
      "optionC_img": null,
      "optionD": "$33954.34 \\text{ঘন সে}.\\text{মি}. (\\text{প্রায়})$",
      "optionD_img": null,
      "answer": "B",
      "chapter": "13",
      "explanation": "ঘনকের ধার $22$ সে.মি.।  ঘনকের আয়তন $22^3 = 10648$ ঘন সে.মি.।  গোলকের ব্যাসার্ধ $11$ সে.মি.।  গোলকের আয়তন $\\frac{4}{3}\\pi (11)^3 \\approx 5575.28$ ঘন সে.মি.।  অনধিকৃত অংশের আয়তন $10648 - 5575.28 \\approx 5072.72$ ঘন সে.মি.।  এটি বিকল্প B এর সাথে প্রায় মিলে যায়।"
    },
    {
      "number": 15,
      "question": "$\\left(x-\\frac{k}{3}\\right)^{4} \\text{এর বিস্তৃতিতে}x^{3} \\text{এর সহগ}-12 \\text{হলে}K \\text{এর মান কত}?$",
      "image": null,
      "optionA": "$-36$",
      "optionA_img": null,
      "optionB": "$-9$",
      "optionB_img": null,
      "optionC": "$9$",
      "optionC_img": null,
      "optionD": "$36$",
      "optionD_img": null,
      "answer": "C",
      "chapter": "10",
      "explanation": "বাইনোমিয়াল বিস্তৃতির সূত্র ব্যবহার করে, $(x - \\frac{k}{3})^4$ এর বিস্তৃতিতে $x^3$ এর সহগ হলো ${4 \\choose 1} (x)^3 (-\\frac{k}{3})^1 = 4x^3(-\\frac{k}{3}) = -\\frac{4k}{3}x^3$।  প্রশ্নানুসারে, $-\\frac{4k}{3} = -12$।  সুতরাং, $4k = 36$, অর্থাৎ $k = 9$।  এটি বিকল্প C এর সাথে মিলে যায়।"
    },
    {
      "number": 16,
      "question": "$\\text{কিছু সংখ্যক লোকের মধ্যে}60 \\text{জন বাংলা}, 35 \\text{জন ইংরেজি এবং}15 \\text{জন বাংলা ও ইংরেজি বলতে পারে}। \\text{দুইটি ভাষার অন্তত একটি ভাষা কতজন বলতে পারে}?$",
      "image": null,
      "optionA": "$10$",
      "optionA_img": null,
      "optionB": "$40$",
      "optionB_img": null,
      "optionC": "$60$",
      "optionC_img": null,
      "optionD": "$80$",
      "optionD_img": null,
      "answer": "D",
      "chapter": "14",
      "explanation": "সমষ্টিকে $U$ দ্বারা প্রকাশ করলে,  $|বাংলা| = 60$, $|ইংরেজি| = 35$, $|বাংলা \\cap ইংরেজি| = 15$।  $|$বাংলা $\\cup$ ইংরেজি$| = |বাংলা| + |ইংরেজি| - |বাংলা \\cap ইংরেজি| = 60 + 35 - 15 = 80$।  অর্থাৎ, 80 জন দুইটি ভাষার অন্তত একটি ভাষা বলতে পারে। এটি বিকল্প D এর সাথে মিলে যায়।"
    },
    {
      "number": 17,
      "question": "$-1560° \\text{কোণটি কোন চতুর্ভাগে থাকবে}?$",
      "image": null,
      "optionA": "$\\text{প্রথম}$",
      "optionA_img": null,
      "optionB": "$\\text{দ্বিতীয়}$",
      "optionB_img": null,
      "optionC": "$\\text{তৃতীয়}$",
      "optionC_img": null,
      "optionD": "$\\text{চতুর্থ}$",
      "optionD_img": null,
      "answer": "C",
      "chapter": "8",
      "explanation": "$-1560^\\circ$ কে $360^\\circ$ দিয়ে ভাগ করলে, $-1560^\\circ = -4(360^\\circ) + 120^\\circ$।  অর্থাৎ, $-1560^\\circ$ এর সমতুল্য কোণ হলো $240^\\circ$।  $240^\\circ$ তৃতীয় চতুর্ভাগে অবস্থিত।  এটি বিকল্প C এর সাথে মিলে যায়।"
    },
    {
      "number": 18,
      "question": "$3x = 5y+15\\text{রেখাটির ঢাল কত}?$",
      "image": null,
      "optionA": "$-\\frac{3}{5}$",
      "optionA_img": null,
      "optionB": "$-\\frac{1}{3}$",
      "optionB_img": null,
      "optionC": "$\\frac{3}{5}$",
      "optionC_img": null,
      "optionD": "$\\frac{5}{3}$",
      "optionD_img": null,
      "answer": "C",
      "chapter": "11",
      "explanation": "$3x = 5y + 15$।  এই রেখার সমীকরণকে $y = mx + c$ আকারে লেখা যায়: $5y = 3x - 15$, অথবা $y = \\frac{3}{5}x - 3$।  সুতরাং, রেখাটির ঢাল $m = \\frac{3}{5}$।  এটি বিকল্প C এর সাথে মিলে যায়।"
    },
    {
      "number": 19,
      "question": "$f(x)=1-3^{x} \\text{হলে}f \\text{এর রেঞ্জ কত}?$",
      "image": null,
      "optionA": "$(-\\infty, 1)$",
      "optionA_img": null,
      "optionB": "$(-\\infty, 1]$",
      "optionB_img": null,
      "optionC": "$(1, \\infty)$",
      "optionC_img": null,
      "optionD": "$(-\\infty, \\infty)$",
      "optionD_img": null,
      "answer": "A",
      "chapter": "9",
      "explanation": "$f(x) = 1 - 3^x$।  যেহেতু $3^x > 0$ সকল $x$ এর জন্য, তাই $1 - 3^x < 1$।  আবার, $3^x$ এর মান 0 এর কাছাকাছি যত ছোট হতে পারে, তাই $1 - 3^x$ এর মান 1 এর কাছাকাছি যত ছোট হতে পারে।  সুতরাং, $f(x)$ এর রেঞ্জ হলো $(-\\infty, 1)$।  এটি বিকল্প A এর সাথে মিলে যায়।"
    },
    {
      "number": 20,
      "question": "$\\text{একটি ছককা নিক্ষেপে}4 \\text{উঠার সম্ভাবনা কোনটি}?$",
      "image": null,
      "optionA": "$\\frac{1}{6}$",
      "optionA_img": null,
      "optionB": "$\\frac{1}{4}$",
      "optionB_img": null,
      "optionC": "$\\frac{2}{3}$",
      "optionC_img": null,
      "optionD": "$\\frac{5}{6}$",
      "optionD_img": null,
      "answer": "A",
      "chapter": "14",
      "explanation": "একটি ছক্কার ছয়টি সমান সম্ভাবনাযুক্ত ফলাফল আছে (1, 2, 3, 4, 5, 6)।  4 উঠার সম্ভাবনা হলো $\\frac{1}{6}$।  এটি বিকল্প A এর সাথে মিলে যায়।"
    },
    {
      "number": 21,
      "question": "$S=\\left\\{(x, y): x^{2}+y^{2}=36\\right. \\text{এবং}\\left.y \\geq 0\\right\\} \\text{হলে}-i. \\text{অন্বয়টি ফাংশন}ii. \\text{অন্বয়টির লেখচিত্র একটি অর্ধবৃত্ত}iii. \\text{অন্বয়টির লেখচিত্র অক্ষের উপরি অর্থতলে থাকবেনিচের কোনটি সঠিক}?$",
      "image": null,
      "optionA": "$i \\text{ও}ii$",
      "optionA_img": null,
      "optionB": "$i \\text{ও}iii$",
      "optionB_img": null,
      "optionC": "$ii \\text{ও}iii$",
      "optionC_img": null,
      "optionD": "$i, ii \\text{ও}iii$",
      "optionD_img": null,
      "answer": "C",
      "chapter": "11",
      "explanation": "$S = \\{(x, y) : x^2 + y^2 = 36, y \\geq 0\\}$।  এটি $x^2 + y^2 = 36$ বৃত্তের উপরের অর্ধেক।  এটি একটি ফাংশন নয় কারণ একটি $x$ এর জন্য দুটি $y$ মান পাওয়া যায়।  লেখচিত্র একটি অর্ধবৃত্ত, এবং অক্ষের নিম্ন অংশে নয়।"
    },
    {
      "number": 22,
      "question": "$\\sin \\theta=-\\frac{\\sqrt{3}}{2} \\text{এবং}-\\frac{\\pi}{2}<\\theta<\\frac{\\pi}{2} \\text{হলে}\\theta \\text{এর মান কত}?$",
      "image": null,
      "optionA": "$\\frac{\\pi}{3}$",
      "optionA_img": null,
      "optionB": "$\\frac{4 \\pi}{3}$",
      "optionB_img": null,
      "optionC": "$\\frac{5 \\pi}{3}$",
      "optionC_img": null,
      "optionD": "$\\frac{11 \\pi}{6}$",
      "optionD_img": null,
      "answer": "C",
      "chapter": "8",
      "explanation": "$\\sin\\theta = -\\frac{\\sqrt{3}}{2}$ এবং $-\\frac{\\pi}{2} < \\theta < \\frac{\\pi}{2}$।  $\\sin^{-1}(-\\frac{\\sqrt{3}}{2}) = -\\frac{\\pi}{3}$।  যেহেতু $-\\frac{\\pi}{2} < -\\frac{\\pi}{3} < \\frac{\\pi}{2}$, তাই  $\\theta = -\\frac{\\pi}{3}$।  তবে, প্রদত্ত বিকল্পগুলোর সাথে মেলে না।  সমস্যাটির ত্রুটি আছে।"
    },
    {
      "number": 23,
      "question": "$12:30 \\text{টায় ঘড়ির ঘণ্টার কাঁটা ও মিনিটের কাঁটার অন্তর্গত কোণ কত ডিগ্রি}?$",
      "image": null,
      "optionA": "$150°$",
      "optionA_img": null,
      "optionB": "$165°$",
      "optionB_img": null,
      "optionC": "$180°$",
      "optionC_img": null,
      "optionD": "$195°$",
      "optionD_img": null,
      "answer": "B",
      "chapter": "3",
      "explanation": "ঘড়ির ঘণ্টার কাঁটা $360^\\circ$ ঘুরে আসে 12 ঘন্টায়।  মিনিটের কাঁটা $360^\\circ$ ঘুরে আসে 60 মিনিটে।  12:30 টায়, মিনিটের কাঁটা $180^\\circ$ এ থাকে, আর ঘণ্টার কাঁটা $15^\\circ \\times 6.5 = 97.5^\\circ$ এ থাকে।  ঘণ্টার কাঁটা এবং মিনিটের কাঁটার মধ্যবর্তী কোণ $180^\\circ - 97.5^\\circ = 82.5^\\circ$ নয়।  সমস্যাটির ত্রুটি আছে।"
    },
    {
      "number": 24,
      "question": "$3x = 5y+15\\text{রেখাটির}Y \\text{ছেদক কত}?$",
      "image": null,
      "optionA": "$-15$",
      "optionA_img": null,
      "optionB": "$-3$",
      "optionB_img": null,
      "optionC": "$3$",
      "optionC_img": null,
      "optionD": "$15$",
      "optionD_img": null,
      "answer": "B",
      "chapter": "11",
      "explanation": "$3x = 5y + 15$।  $Y$ ছেদক নির্ণয় করতে, $x = 0$ বসাই: $0 = 5y + 15$, অর্থাৎ $5y = -15$, $y = -3$।  সুতরাং, $Y$ ছেদক $-3$।  এটি বিকল্প B এর সাথে মিলে যায়।"
    },
    {
      "number": 25,
      "question": "$7^{2 x-3}=6^{2 x-3} \\text{সমীকরণের সমাধান কোনটি}?$",
      "image": null,
      "optionA": "$\\frac{2}{3}$",
      "optionA_img": null,
      "optionB": "$\\frac{6}{7}$",
      "optionB_img": null,
      "optionC": "$\\frac{7}{6}$",
      "optionC_img": null,
      "optionD": "$\\frac{3}{2}$",
      "optionD_img": null,
      "answer": "D",
      "chapter": "9",
      "explanation": "$7^{2x - 3} = 6^{2x - 3}$।  যেহেতু ভিত্তিগুলো সমান নয়, তাই ঘাতগুলো শুধুমাত্র তখন সমান হতে পারে যদি ঘাত শূন্য হয়।  সুতরাং, $2x - 3 = 0$, অর্থাৎ $2x = 3$, $x = \\frac{3}{2}$।  এটি বিকল্প D এর সাথে মিলে যায়।"
    }
  ]
}